{"title":"Combined feed","url":"https://factcheckr.github.io/daum_news/all.xml","elements":[{"title":"MIchigan State Shooting (다음 뉴스 ─ 전체기사 ─ 최신)","contents":"연합뉴스<span class=\"txt_bar\"> · </span><span class=\"info_time\">05:18</span>","link":"https://v.daum.net/v/20230215051844472","retrieved":1676405934715},{"title":"MIchigan State Shooting (다음 뉴스 ─ 전체기사 ─ 최신)","contents":"연합뉴스<span class=\"txt_bar\"> · </span><span class=\"info_time\">05:18</span>","link":"https://v.daum.net/v/20230215051841471","retrieved":1676405934715},{"title":"MIchigan State Shooting (다음 뉴스 ─ 전체기사 ─ 최신)","contents":"연합뉴스<span class=\"txt_bar\"> · </span><span class=\"info_time\">05:18</span>","link":"https://v.daum.net/v/20230215051837470","retrieved":1676405934716},{"title":"바이든,100명째 연방판사 인준에 한국계 예로들며 \"다양성 확대\" (다음 뉴스 ─ 전체기사 ─ 최신)","contents":"연합뉴스<span class=\"txt_bar\"> · </span><span class=\"info_time\">05:18</span>","link":"https://v.daum.net/v/20230215051828469","retrieved":1676405934725},{"title":"금융당국, '돈 잔치' 점검 예고…은행 향한 연속 '견제구' (다음 뉴스 ─ 전체기사 ─ 최신)","contents":"노컷뉴스<span class=\"txt_bar\"> · </span><span class=\"info_time\">05:18</span>","link":"https://v.daum.net/v/20230215051801468","retrieved":1676405934736},{"title":"Turkey Syria Earthquake (다음 뉴스 ─ 전체기사 ─ 최신)","contents":"연합뉴스<span class=\"txt_bar\"> · </span><span class=\"info_time\">05:17</span>","link":"https://v.daum.net/v/20230215051753467","retrieved":1676405934738},{"title":"Lottery Jackpot (다음 뉴스 ─ 전체기사 ─ 최신)","contents":"연합뉴스<span class=\"txt_bar\"> · </span><span class=\"info_time\">05:17</span>","link":"https://v.daum.net/v/20230215051750466","retrieved":1676405934739},{"title":"Lottery Jackpot (다음 뉴스 ─ 전체기사 ─ 최신)","contents":"연합뉴스<span class=\"txt_bar\"> · </span><span class=\"info_time\">05:17</span>","link":"https://v.daum.net/v/20230215051746465","retrieved":1676405934742},{"title":"[Kim Seong-kon] 'Where to?' Which path should we take? (다음 뉴스 ─ 전체기사 ─ 최신)","contents":"코리아헤럴드<span class=\"txt_bar\"> · </span><span class=\"info_time\">05:17</span>","link":"https://v.daum.net/v/20230215051725464","retrieved":1676405934743},{"title":"Dismemberment Killing (다음 뉴스 ─ 전체기사 ─ 최신)","contents":"연합뉴스<span class=\"txt_bar\"> · </span><span class=\"info_time\">05:17</span>","link":"https://v.daum.net/v/20230215051712463","retrieved":1676405934752},{"title":"Dismemberment Killing (다음 뉴스 ─ 전체기사 ─ 최신)","contents":"연합뉴스<span class=\"txt_bar\"> · </span><span class=\"info_time\">05:17</span>","link":"https://v.daum.net/v/20230215051709462","retrieved":1676405934752},{"title":"강남·용산 고가 오피스텔 사업 잇단 위기… 수천억대 대출금 미상환 (다음 뉴스 ─ 전체기사 ─ 최신)","contents":"머니S<span class=\"txt_bar\"> · </span><span class=\"info_time\">05:17</span>","link":"https://v.daum.net/v/20230215051706461","retrieved":1676405934753},{"title":"Turkey Syria Earthquake (다음 뉴스 ─ 전체기사 ─ 최신)","contents":"연합뉴스<span class=\"txt_bar\"> · </span><span class=\"info_time\">05:17</span>","link":"https://v.daum.net/v/20230215051706460","retrieved":1676405934754},{"title":"'WBC 이끌 양현종의 손' (다음 뉴스 ─ 전체기사 ─ 최신)","contents":"뉴스1<span class=\"txt_bar\"> · </span><span class=\"info_time\">05:17</span>","link":"https://v.daum.net/v/20230215051704459","retrieved":1676405934754},{"title":"Turkey Syria Earthquake (다음 뉴스 ─ 전체기사 ─ 최신)","contents":"연합뉴스<span class=\"txt_bar\"> · </span><span class=\"info_time\">05:17</span>","link":"https://v.daum.net/v/20230215051702458","retrieved":1676405934754},{"title":"\"성폭행 당했다\" 전 연인 허위 고소한 블로거 '도도맘', 결국 유죄 (다음 뉴스 ─ 전체기사 ─ 사회)","contents":"파이낸셜뉴스<span class=\"txt_bar\"> · </span><span class=\"info_time\">05:15</span>","link":"https://v.daum.net/v/20230215051504444","retrieved":1676405951644},{"title":"타임라인 꼬인 연금개혁…5월 전 '밑그림' 어려운 이유는? (다음 뉴스 ─ 전체기사 ─ 사회)","contents":"노컷뉴스<span class=\"txt_bar\"> · </span><span class=\"info_time\">05:12</span>","link":"https://v.daum.net/v/20230215051200417","retrieved":1676405951646},{"title":"제3의료진 'PA간호사' 벌써 1만명…병원 \"더 뽑자\" 法은 \"무면허\" (다음 뉴스 ─ 전체기사 ─ 사회)","contents":"뉴스1<span class=\"txt_bar\"> · </span><span class=\"info_time\">05:10</span>","link":"https://v.daum.net/v/20230215051006381","retrieved":1676405951651},{"title":"“삼겹살과 번개탄 주문...?” 배달 기사가 사람 살렸다 (다음 뉴스 ─ 전체기사 ─ 사회)","contents":"국민일보<span class=\"txt_bar\"> · </span><span class=\"info_time\">05:09</span>","link":"https://v.daum.net/v/20230215050917370","retrieved":1676405951652},{"title":"[법조계에 물어보니 109] 검찰, 부결될 것 알면서 왜 이재명 구속영장 청구할까? (다음 뉴스 ─ 전체기사 ─ 사회)","contents":"데일리안<span class=\"txt_bar\"> · </span><span class=\"info_time\">05:09</span>","link":"https://v.daum.net/v/20230215050905367","retrieved":1676405951653},{"title":"[유보통합 ②] \"우리가 어떻게 같은 자격의 교사인가?\"…통일보다 힘든 '교사통합' (다음 뉴스 ─ 전체기사 ─ 사회)","contents":"데일리안<span class=\"txt_bar\"> · </span><span class=\"info_time\">05:06</span>","link":"https://v.daum.net/v/20230215050603344","retrieved":1676405951654},{"title":"\"사필귀정\"…독재정권 특허권 강탈, 50년 만의 '진실규명' (다음 뉴스 ─ 전체기사 ─ 사회)","contents":"노컷뉴스<span class=\"txt_bar\"> · </span><span class=\"info_time\">05:06</span>","link":"https://v.daum.net/v/20230215050602341","retrieved":1676405951656},{"title":"정쟁화된 도이치모터스 판결문...“대통령실 입장문, 사안 의도적 축소” (다음 뉴스 ─ 전체기사 ─ 사회)","contents":"한겨레<span class=\"txt_bar\"> · </span><span class=\"info_time\">05:05</span>","link":"https://v.daum.net/v/20230215050509328","retrieved":1676405951657},{"title":"[영상:THISCovery]초콜릿은 어떻게 탄생한 걸까? (다음 뉴스 ─ 전체기사 ─ 사회)","contents":"한겨레<span class=\"txt_bar\"> · </span><span class=\"info_time\">05:05</span>","link":"https://v.daum.net/v/20230215050506325","retrieved":1676405951658},{"title":"수면 위로 떠오른 대중교통 노인 무임승차 쟁점은? (다음 뉴스 ─ 전체기사 ─ 사회)","contents":"한겨레<span class=\"txt_bar\"> · </span><span class=\"info_time\">05:05</span>","link":"https://v.daum.net/v/20230215050501322","retrieved":1676405951659},{"title":"[인사] (다음 뉴스 ─ 전체기사 ─ 사회)","contents":"서울신문<span class=\"txt_bar\"> · </span><span class=\"info_time\">05:03</span>","link":"https://v.daum.net/v/20230215050338280","retrieved":1676405951669},{"title":"[부고] (다음 뉴스 ─ 전체기사 ─ 사회)","contents":"서울신문<span class=\"txt_bar\"> · </span><span class=\"info_time\">05:03</span>","link":"https://v.daum.net/v/20230215050337278","retrieved":1676405951670},{"title":"자소서 폐지,학생부 항목 축소…교과에        충실 (다음 뉴스 ─ 전체기사 ─ 사회)","contents":"서울신문<span class=\"txt_bar\"> · </span><span class=\"info_time\">05:03</span>","link":"https://v.daum.net/v/20230215050333274","retrieved":1676405951670},{"title":"경북 군위농협, 영농자재 무상이용권 지급 (다음 뉴스 ─ 전체기사 ─ 사회)","contents":"농민신문<span class=\"txt_bar\"> · </span><span class=\"info_time\">05:03</span>","link":"https://v.daum.net/v/20230215050331272","retrieved":1676405951670},{"title":"광주광역시 평동농협, 전체 조합원 단체상해보험 가입 지원 (다음 뉴스 ─ 전체기사 ─ 사회)","contents":"농민신문<span class=\"txt_bar\"> · </span><span class=\"info_time\">05:03</span>","link":"https://v.daum.net/v/20230215050325264","retrieved":1676405951674},{"title":"정성호 “이대로면 이재명 대통령, 알리바이 중요”…전여옥 “조폭영화서 나오던 대사” (다음 뉴스 ─ 전체기사 ─ 정치)","contents":"디지털타임스<span class=\"txt_bar\"> · </span><span class=\"info_time\">05:16</span>","link":"https://v.daum.net/v/20230215051613452","retrieved":1676405962469},{"title":"국민공감, 네 번째 모임 '탄소중립' 특강…참석 규모도 주목 (다음 뉴스 ─ 전체기사 ─ 정치)","contents":"뉴스1<span class=\"txt_bar\"> · </span><span class=\"info_time\">05:15</span>","link":"https://v.daum.net/v/20230215051502443","retrieved":1676405962469},{"title":"이재명, 개딸에 “수박 문자폭탄 그만…나도 ‘찢’에 상처” (다음 뉴스 ─ 전체기사 ─ 정치)","contents":"국민일보<span class=\"txt_bar\"> · </span><span class=\"info_time\">05:10</span>","link":"https://v.daum.net/v/20230215051015385","retrieved":1676405962469},{"title":"여야 \"보훈부 격상·재외 동포청 신설 합의\"...여가부 결론 못내 (다음 뉴스 ─ 전체기사 ─ 정치)","contents":"YTN<span class=\"txt_bar\"> · </span><span class=\"info_time\">05:07</span>","link":"https://v.daum.net/v/20230215050715356","retrieved":1676405962469},{"title":"상가·오피스텔 시가표준액 납세자 의견 듣는다 (다음 뉴스 ─ 전체기사 ─ 정치)","contents":"서울신문<span class=\"txt_bar\"> · </span><span class=\"info_time\">05:03</span>","link":"https://v.daum.net/v/20230215050327268","retrieved":1676405962472},{"title":"대통령실 “김건희 여사 계좌 활용됐다 해서 주가조작 가담 아냐” (다음 뉴스 ─ 전체기사 ─ 정치)","contents":"세계일보<span class=\"txt_bar\"> · </span><span class=\"info_time\">05:03</span>","link":"https://v.daum.net/v/20230215050317253","retrieved":1676405962472},{"title":"“똑똑! 새해 인사 드려요” 금천주민 다독다독[현장 행정] (다음 뉴스 ─ 전체기사 ─ 정치)","contents":"서울신문<span class=\"txt_bar\"> · </span><span class=\"info_time\">05:03</span>","link":"https://v.daum.net/v/20230215050305231","retrieved":1676405962473},{"title":"서울대서 열공… 관악시민대학 수강생 찾아요 (다음 뉴스 ─ 전체기사 ─ 정치)","contents":"서울신문<span class=\"txt_bar\"> · </span><span class=\"info_time\">05:03</span>","link":"https://v.daum.net/v/20230215050304230","retrieved":1676405962473},{"title":"“‘양자대결’ 김기현 52% vs 안철수 42%” (다음 뉴스 ─ 전체기사 ─ 정치)","contents":"세계일보<span class=\"txt_bar\"> · </span><span class=\"info_time\">05:03</span>","link":"https://v.daum.net/v/20230215050302229","retrieved":1676405962477},{"title":"중곡~군자역 버스노선 생겼다…광진 주민 대중교통 편의 ‘쑥’ (다음 뉴스 ─ 전체기사 ─ 정치)","contents":"서울신문<span class=\"txt_bar\"> · </span><span class=\"info_time\">05:03</span>","link":"https://v.daum.net/v/20230215050302228","retrieved":1676405962480},{"title":"친환경·마음건강… 송파 복지관 만족도 높여요 (다음 뉴스 ─ 전체기사 ─ 정치)","contents":"서울신문<span class=\"txt_bar\"> · </span><span class=\"info_time\">05:03</span>","link":"https://v.daum.net/v/20230215050301226","retrieved":1676405962481},{"title":"서대문, 신축 빌라 인근 부동산중개소 점검 (다음 뉴스 ─ 전체기사 ─ 정치)","contents":"서울신문<span class=\"txt_bar\"> · </span><span class=\"info_time\">05:03</span>","link":"https://v.daum.net/v/20230215050300225","retrieved":1676405962483},{"title":"구로, 찾아가는 결핵 검진 사업 확대 (다음 뉴스 ─ 전체기사 ─ 정치)","contents":"서울신문<span class=\"txt_bar\"> · </span><span class=\"info_time\">05:02</span>","link":"https://v.daum.net/v/20230215050259222","retrieved":1676405962485},{"title":"강서 ‘스타 공무원’에 파격 인센티브 (다음 뉴스 ─ 전체기사 ─ 정치)","contents":"서울신문<span class=\"txt_bar\"> · </span><span class=\"info_time\">05:02</span>","link":"https://v.daum.net/v/20230215050256218","retrieved":1676405962487},{"title":"중랑 “청소년 정책, 함께 만들어요” (다음 뉴스 ─ 전체기사 ─ 정치)","contents":"서울신문<span class=\"txt_bar\"> · </span><span class=\"info_time\">05:02</span>","link":"https://v.daum.net/v/20230215050253216","retrieved":1676405962489},{"title":"최대 매출 쓴 동원F&B, 원가 급등에도 수익성 방어 선방 (다음 뉴스 ─ 전체기사 ─ 경제)","contents":"머니S<span class=\"txt_bar\"> · </span><span class=\"info_time\">05:19</span>","link":"https://v.daum.net/v/20230215051906477","retrieved":1676405973016},{"title":"금융당국, '돈 잔치' 점검 예고…은행 향한 연속 '견제구' (다음 뉴스 ─ 전체기사 ─ 경제)","contents":"노컷뉴스<span class=\"txt_bar\"> · </span><span class=\"info_time\">05:18</span>","link":"https://v.daum.net/v/20230215051801468","retrieved":1676405973019},{"title":"강남·용산 고가 오피스텔 사업 잇단 위기… 수천억대 대출금 미상환 (다음 뉴스 ─ 전체기사 ─ 경제)","contents":"머니S<span class=\"txt_bar\"> · </span><span class=\"info_time\">05:17</span>","link":"https://v.daum.net/v/20230215051706461","retrieved":1676405973019},{"title":"'나보타 중단 위기' 대웅제약, 새 보툴리눔 톡신 내놓을까 (다음 뉴스 ─ 전체기사 ─ 경제)","contents":"머니S<span class=\"txt_bar\"> · </span><span class=\"info_time\">05:13</span>","link":"https://v.daum.net/v/20230215051306424","retrieved":1676405973020},{"title":"'AI 보안' 샌즈랩, 코스닥 입성… IPO 흥행 온기로 '따상' 직행할까 (다음 뉴스 ─ 전체기사 ─ 경제)","contents":"머니S<span class=\"txt_bar\"> · </span><span class=\"info_time\">05:11</span>","link":"https://v.daum.net/v/20230215051118407","retrieved":1676405973021},{"title":"국회 환노위, 15일 노란봉투법 논의… 경제계, 입법 저지 총력 (다음 뉴스 ─ 전체기사 ─ 경제)","contents":"머니S<span class=\"txt_bar\"> · </span><span class=\"info_time\">05:11</span>","link":"https://v.daum.net/v/20230215051104401","retrieved":1676405973022},{"title":"[청계광장] 스키 타다가… 어깨 통증, 가볍게 보면 안되는 이유 (다음 뉴스 ─ 전체기사 ─ 경제)","contents":"머니S<span class=\"txt_bar\"> · </span><span class=\"info_time\">05:10</span>","link":"https://v.daum.net/v/20230215051021387","retrieved":1676405973023},{"title":"ETF 90兆 시대…올해 금리형·채권형 순자산 '쑥' (다음 뉴스 ─ 전체기사 ─ 경제)","contents":"이데일리<span class=\"txt_bar\"> · </span><span class=\"info_time\">05:10</span>","link":"https://v.daum.net/v/20230215051020386","retrieved":1676405973024},{"title":"尹 친원전 정책에…작년 발전량 ‘역대 최대’ (다음 뉴스 ─ 전체기사 ─ 경제)","contents":"이데일리<span class=\"txt_bar\"> · </span><span class=\"info_time\">05:10</span>","link":"https://v.daum.net/v/20230215051009384","retrieved":1676405973025},{"title":"\"올해 강남 집값 추락할 것\"…하락 예언한 교수의 新 경고[부릿지] (다음 뉴스 ─ 전체기사 ─ 경제)","contents":"머니투데이<span class=\"txt_bar\"> · </span><span class=\"info_time\">05:10</span>","link":"https://v.daum.net/v/20230215051007382","retrieved":1676405973025},{"title":"반도체 혹한기에도 1월 '깜짝 실적' 낸 TSMC…삼성·SK는 어떻길래 (다음 뉴스 ─ 전체기사 ─ 경제)","contents":"뉴스1<span class=\"txt_bar\"> · </span><span class=\"info_time\">05:10</span>","link":"https://v.daum.net/v/20230215051005380","retrieved":1676405973026},{"title":"\"인천공항 노린다\" 中면세점에 '긴장' (다음 뉴스 ─ 전체기사 ─ 경제)","contents":"머니투데이<span class=\"txt_bar\"> · </span><span class=\"info_time\">05:10</span>","link":"https://v.daum.net/v/20230215051002377","retrieved":1676405973028},{"title":"보험금 늦게 주는 보험사 어디?… 금감원, 공시의무 강화한다 (다음 뉴스 ─ 전체기사 ─ 경제)","contents":"머니S<span class=\"txt_bar\"> · </span><span class=\"info_time\">05:07</span>","link":"https://v.daum.net/v/20230215050704354","retrieved":1676405973029},{"title":"5% 예금 실종에 코픽스 더 떨어진다… 주담대 이자 줄어들까 (다음 뉴스 ─ 전체기사 ─ 경제)","contents":"머니S<span class=\"txt_bar\"> · </span><span class=\"info_time\">05:06</span>","link":"https://v.daum.net/v/20230215050606346","retrieved":1676405973030},{"title":"프랑스 작년 4분기 실업률 15년만에 최저…연금개혁에 힘 실릴까 (다음 뉴스 ─ 전체기사 ─ 경제)","contents":"SBS Biz<span class=\"txt_bar\"> · </span><span class=\"info_time\">05:06</span>","link":"https://v.daum.net/v/20230215050602343","retrieved":1676405973031},{"title":"Fashion Brandon Maxwell - Bryant (다음 뉴스 ─ 전체기사 ─ 국제)","contents":"연합뉴스<span class=\"txt_bar\"> · </span><span class=\"info_time\">05:19</span>","link":"https://v.daum.net/v/20230215051933478","retrieved":1676405983307},{"title":"영-EU, 브렉시트 갈등 매듭짓나…북아일랜드 협약 타결 임박한듯 (다음 뉴스 ─ 전체기사 ─ 국제)","contents":"연합뉴스<span class=\"txt_bar\"> · </span><span class=\"info_time\">05:19</span>","link":"https://v.daum.net/v/20230215051900476","retrieved":1676405983312},{"title":"MIchigan State Shooting (다음 뉴스 ─ 전체기사 ─ 국제)","contents":"연합뉴스<span class=\"txt_bar\"> · </span><span class=\"info_time\">05:18</span>","link":"https://v.daum.net/v/20230215051855475","retrieved":1676405983316},{"title":"MIchigan State Shooting (다음 뉴스 ─ 전체기사 ─ 국제)","contents":"연합뉴스<span class=\"txt_bar\"> · </span><span class=\"info_time\">05:18</span>","link":"https://v.daum.net/v/20230215051852474","retrieved":1676405983318},{"title":"MIchigan State Shooting (다음 뉴스 ─ 전체기사 ─ 국제)","contents":"연합뉴스<span class=\"txt_bar\"> · </span><span class=\"info_time\">05:18</span>","link":"https://v.daum.net/v/20230215051848473","retrieved":1676405983320},{"title":"MIchigan State Shooting (다음 뉴스 ─ 전체기사 ─ 국제)","contents":"연합뉴스<span class=\"txt_bar\"> · </span><span class=\"info_time\">05:18</span>","link":"https://v.daum.net/v/20230215051844472","retrieved":1676405983321},{"title":"MIchigan State Shooting (다음 뉴스 ─ 전체기사 ─ 국제)","contents":"연합뉴스<span class=\"txt_bar\"> · </span><span class=\"info_time\">05:18</span>","link":"https://v.daum.net/v/20230215051841471","retrieved":1676405983324},{"title":"MIchigan State Shooting (다음 뉴스 ─ 전체기사 ─ 국제)","contents":"연합뉴스<span class=\"txt_bar\"> · </span><span class=\"info_time\">05:18</span>","link":"https://v.daum.net/v/20230215051837470","retrieved":1676405983327},{"title":"바이든,100명째 연방판사 인준에 한국계 예로들며 \"다양성 확대\" (다음 뉴스 ─ 전체기사 ─ 국제)","contents":"연합뉴스<span class=\"txt_bar\"> · </span><span class=\"info_time\">05:18</span>","link":"https://v.daum.net/v/20230215051828469","retrieved":1676405983328},{"title":"Turkey Syria Earthquake (다음 뉴스 ─ 전체기사 ─ 국제)","contents":"연합뉴스<span class=\"txt_bar\"> · </span><span class=\"info_time\">05:17</span>","link":"https://v.daum.net/v/20230215051753467","retrieved":1676405983331},{"title":"Lottery Jackpot (다음 뉴스 ─ 전체기사 ─ 국제)","contents":"연합뉴스<span class=\"txt_bar\"> · </span><span class=\"info_time\">05:17</span>","link":"https://v.daum.net/v/20230215051750466","retrieved":1676405983333},{"title":"Lottery Jackpot (다음 뉴스 ─ 전체기사 ─ 국제)","contents":"연합뉴스<span class=\"txt_bar\"> · </span><span class=\"info_time\">05:17</span>","link":"https://v.daum.net/v/20230215051746465","retrieved":1676405983335},{"title":"Dismemberment Killing (다음 뉴스 ─ 전체기사 ─ 국제)","contents":"연합뉴스<span class=\"txt_bar\"> · </span><span class=\"info_time\">05:17</span>","link":"https://v.daum.net/v/20230215051712463","retrieved":1676405983337},{"title":"Dismemberment Killing (다음 뉴스 ─ 전체기사 ─ 국제)","contents":"연합뉴스<span class=\"txt_bar\"> · </span><span class=\"info_time\">05:17</span>","link":"https://v.daum.net/v/20230215051709462","retrieved":1676405983339},{"title":"Turkey Syria Earthquake (다음 뉴스 ─ 전체기사 ─ 국제)","contents":"연합뉴스<span class=\"txt_bar\"> · </span><span class=\"info_time\">05:17</span>","link":"https://v.daum.net/v/20230215051706460","retrieved":1676405983341},{"title":"하이브 대표 \"방시혁, 민희진 바쁘다. 이수만도 경영 참여 없을 것\" (다음 뉴스 ─ 전체기사 ─ 문화)","contents":"파이낸셜뉴스<span class=\"txt_bar\"> · </span><span class=\"info_time\">05:05</span>","link":"https://v.daum.net/v/20230215050505324","retrieved":1676405999544},{"title":"[헬스S] 노령·쌍둥이 임신, 제왕절개 산모 '이것' 위험 높다 (다음 뉴스 ─ 전체기사 ─ 문화)","contents":"머니S<span class=\"txt_bar\"> · </span><span class=\"info_time\">05:04</span>","link":"https://v.daum.net/v/20230215050405298","retrieved":1676405999545},{"title":"교도관, 여성 일등항해사, 남성 간호사의 삶이란… (다음 뉴스 ─ 전체기사 ─ 문화)","contents":"서울신문<span class=\"txt_bar\"> · </span><span class=\"info_time\">05:03</span>","link":"https://v.daum.net/v/20230215050355291","retrieved":1676405999546},{"title":"“관객 마음 치유하는 연기… ‘영웅’의 힘이죠” (다음 뉴스 ─ 전체기사 ─ 문화)","contents":"서울신문<span class=\"txt_bar\"> · </span><span class=\"info_time\">05:03</span>","link":"https://v.daum.net/v/20230215050352290","retrieved":1676405999547},{"title":"자연 벗삼은 확트인 서가… 美 충전완료 (다음 뉴스 ─ 전체기사 ─ 문화)","contents":"서울신문<span class=\"txt_bar\"> · </span><span class=\"info_time\">05:03</span>","link":"https://v.daum.net/v/20230215050350289","retrieved":1676405999548},{"title":"“여러 장르 균형·조화로 ‘정동극장 색깔’ 낼 것” (다음 뉴스 ─ 전체기사 ─ 문화)","contents":"서울신문<span class=\"txt_bar\"> · </span><span class=\"info_time\">05:03</span>","link":"https://v.daum.net/v/20230215050342283","retrieved":1676405999556},{"title":"조성진, 英 바비칸센터 솔로 무대 성공적 (다음 뉴스 ─ 전체기사 ─ 문화)","contents":"서울신문<span class=\"txt_bar\"> · </span><span class=\"info_time\">05:03</span>","link":"https://v.daum.net/v/20230215050337279","retrieved":1676405999556},{"title":"[SNS로 보는 세상] “형제여, 힘내세요!” 기부 물결 (다음 뉴스 ─ 전체기사 ─ 문화)","contents":"농민신문<span class=\"txt_bar\"> · </span><span class=\"info_time\">05:03</span>","link":"https://v.daum.net/v/20230215050333275","retrieved":1676405999556},{"title":"금융예수금 1000억 돌파…평창영월정선축협 영월지점 (다음 뉴스 ─ 전체기사 ─ 문화)","contents":"농민신문<span class=\"txt_bar\"> · </span><span class=\"info_time\">05:03</span>","link":"https://v.daum.net/v/20230215050320256","retrieved":1676405999558},{"title":"농협 영우회, 영동군에 고향기부금 250만원 전달 (다음 뉴스 ─ 전체기사 ─ 문화)","contents":"농민신문<span class=\"txt_bar\"> · </span><span class=\"info_time\">05:03</span>","link":"https://v.daum.net/v/20230215050309241","retrieved":1676405999568},{"title":"‘정성 듬뿍’ 고추장·된장…농가소득 견인 기대 (다음 뉴스 ─ 전체기사 ─ 문화)","contents":"농민신문<span class=\"txt_bar\"> · </span><span class=\"info_time\">05:03</span>","link":"https://v.daum.net/v/20230215050306232","retrieved":1676405999570},{"title":"[우리 술 답사기] 술잔 비워도 감도는 보리향, 칠십년 위엄지킨 장군의 술 (다음 뉴스 ─ 전체기사 ─ 문화)","contents":"농민신문<span class=\"txt_bar\"> · </span><span class=\"info_time\">05:02</span>","link":"https://v.daum.net/v/20230215050217165","retrieved":1676405999572},{"title":"[귀농·귀촌 부동산 이야기] 땅 구하기는 결혼과 같아⋯좋은 땅은 만들어지는 것 (다음 뉴스 ─ 전체기사 ─ 문화)","contents":"농민신문<span class=\"txt_bar\"> · </span><span class=\"info_time\">05:01</span>","link":"https://v.daum.net/v/20230215050135134","retrieved":1676405999574},{"title":"[가족농 열전 백년농부] 아내 건강 위해 잠시 머물려다 마을지도자로 ‘인생 2막’ (다음 뉴스 ─ 전체기사 ─ 문화)","contents":"농민신문<span class=\"txt_bar\"> · </span><span class=\"info_time\">05:01</span>","link":"https://v.daum.net/v/20230215050133133","retrieved":1676405999578},{"title":"‘봄의 색계(色界)’ 각양각색 다육식물 (다음 뉴스 ─ 전체기사 ─ 문화)","contents":"농민신문<span class=\"txt_bar\"> · </span><span class=\"info_time\">05:01</span>","link":"https://v.daum.net/v/20230215050132132","retrieved":1676405999580},{"title":"고수, ‘♥11세 연하’ 명언 올려… “여자 말을 잘 듣자” [★SHOT!] (다음 뉴스 ─ 전체기사 ─ 연예)","contents":"OSEN<span class=\"txt_bar\"> · </span><span class=\"info_time\">05:15</span>","link":"https://v.daum.net/v/20230215051520446","retrieved":1676406014848},{"title":"위하준, 점점 빠져드는 미소...해피 밸런타인데이 (다음 뉴스 ─ 전체기사 ─ 연예)","contents":"텐아시아<span class=\"txt_bar\"> · </span><span class=\"info_time\">05:14</span>","link":"https://v.daum.net/v/20230215051401433","retrieved":1676406014849},{"title":"레전드 뮤지컬 영화 '그리스' 프리퀄 나왔다...4월 공개 (다음 뉴스 ─ 전체기사 ─ 연예)","contents":"TV리포트<span class=\"txt_bar\"> · </span><span class=\"info_time\">05:10</span>","link":"https://v.daum.net/v/20230215051031391","retrieved":1676406014849},{"title":"김소현 \"♥손준호, 사귄 지 이틀 만 부모님께 인사하러와…母 반응은?\" [신랑수업] (다음 뉴스 ─ 전체기사 ─ 연예)","contents":"마이데일리<span class=\"txt_bar\"> · </span><span class=\"info_time\">05:10</span>","link":"https://v.daum.net/v/20230215051004379","retrieved":1676406014849},{"title":"공훈x남승민, '전국노래자랑'으로 맺은 인연→'불트' 듀엣까지 [RE:TV] (다음 뉴스 ─ 전체기사 ─ 연예)","contents":"뉴스1<span class=\"txt_bar\"> · </span><span class=\"info_time\">05:10</span>","link":"https://v.daum.net/v/20230215051003378","retrieved":1676406014849},{"title":"트라이비 송선..상큼하트' [사진] (다음 뉴스 ─ 전체기사 ─ 연예)","contents":"OSEN<span class=\"txt_bar\"> · </span><span class=\"info_time\">05:09</span>","link":"https://v.daum.net/v/20230215050924373","retrieved":1676406014849},{"title":"\"지X하고 자빠졌네\" 탁재훈, 김준호♥김지민 애정행각에 '헛웃음' [돌싱포맨](MD리뷰) (다음 뉴스 ─ 전체기사 ─ 연예)","contents":"마이데일리<span class=\"txt_bar\"> · </span><span class=\"info_time\">05:04</span>","link":"https://v.daum.net/v/20230215050407300","retrieved":1676406014849},{"title":"[TF인터뷰②] 정민찬 \"미스터트롯2' 끝났지만 '발레 트로트' 이제 시작\" (다음 뉴스 ─ 전체기사 ─ 연예)","contents":"더팩트<span class=\"txt_bar\"> · </span><span class=\"info_time\">05:01</span>","link":"https://v.daum.net/v/20230215050112106","retrieved":1676406014854},{"title":"아이키, 뉴진스 따라하기?...귀여운 반전매력 (다음 뉴스 ─ 전체기사 ─ 연예)","contents":"텐아시아<span class=\"txt_bar\"> · </span><span class=\"info_time\">05:01</span>","link":"https://v.daum.net/v/20230215050101097","retrieved":1676406014854},{"title":"[SM·이수만發 K팝 격변④]하이브, 유니버설·소니·워너 대항마? (다음 뉴스 ─ 전체기사 ─ 연예)","contents":"뉴시스<span class=\"txt_bar\"> · </span><span class=\"info_time\">05:00</span>","link":"https://v.daum.net/v/20230215050017015","retrieved":1676406014855},{"title":"[TF인터뷰①] 정민찬 \"'미스터트롯2' 덕에 실명 직전 母에 효도\" (다음 뉴스 ─ 전체기사 ─ 연예)","contents":"더팩트<span class=\"txt_bar\"> · </span><span class=\"info_time\">05:00</span>","link":"https://v.daum.net/v/20230215050009987","retrieved":1676406014858},{"title":"임현주♥다니엘 튜더, 혼인신고 완료…\"이제 취소도 안되고\" [전문] (다음 뉴스 ─ 전체기사 ─ 연예)","contents":"엑스포츠뉴스<span class=\"txt_bar\"> · </span><span class=\"info_time\">05:00</span>","link":"https://v.daum.net/v/20230215050008985","retrieved":1676406014860},{"title":"라임라잇 \"엄마, 아빠가 자랑스러워하는 딸…더 열심히 할게요!\" [MD인터뷰] (다음 뉴스 ─ 전체기사 ─ 연예)","contents":"마이데일리<span class=\"txt_bar\"> · </span><span class=\"info_time\">05:00</span>","link":"https://v.daum.net/v/20230215050007981","retrieved":1676406014864},{"title":"종영 '트롤리' 박희순 \"내 죄 수치스러워\"..극단적 선택 시도→자수 [★밤TV] (다음 뉴스 ─ 전체기사 ─ 연예)","contents":"스타뉴스<span class=\"txt_bar\"> · </span><span class=\"info_time\">05:00</span>","link":"https://v.daum.net/v/20230215050002970","retrieved":1676406014865},{"title":"김나영♥마이큐, '그동안 숨겨왔던 투샷' 최초공개…SNS 댓글 폭발 (다음 뉴스 ─ 전체기사 ─ 연예)","contents":"스포츠조선<span class=\"txt_bar\"> · </span><span class=\"info_time\">04:52</span>","link":"https://v.daum.net/v/20230215045235913","retrieved":1676406014868},{"title":"\"야구 못하나 싶었는데…한화 감사합니다\" FA 마음고생 끝, 이명기 새출발 (다음 뉴스 ─ 전체기사 ─ 스포츠)","contents":"OSEN<span class=\"txt_bar\"> · </span><span class=\"info_time\">05:20</span>","link":"https://v.daum.net/v/20230215052019490","retrieved":1676406030318},{"title":"'WBC 이끌 양현종의 손' (다음 뉴스 ─ 전체기사 ─ 스포츠)","contents":"뉴스1<span class=\"txt_bar\"> · </span><span class=\"info_time\">05:17</span>","link":"https://v.daum.net/v/20230215051704459","retrieved":1676406030320},{"title":"훈련 모습 살펴보는 진갑용 코치 (다음 뉴스 ─ 전체기사 ─ 스포츠)","contents":"뉴스1<span class=\"txt_bar\"> · </span><span class=\"info_time\">05:16</span>","link":"https://v.daum.net/v/20230215051656456","retrieved":1676406030321},{"title":"[토트넘 밀란] '7분 만에 무너졌다' 토트넘, 밀란에 선제골 허용(전반 진행) (다음 뉴스 ─ 전체기사 ─ 스포츠)","contents":"인터풋볼<span class=\"txt_bar\"> · </span><span class=\"info_time\">05:15</span>","link":"https://v.daum.net/v/20230215051509445","retrieved":1676406030328},{"title":"한승택, '시즌 1호 홈런' [사진] (다음 뉴스 ─ 전체기사 ─ 스포츠)","contents":"OSEN<span class=\"txt_bar\"> · </span><span class=\"info_time\">05:14</span>","link":"https://v.daum.net/v/20230215051443438","retrieved":1676406030328},{"title":"미소 보이는 김기태 KT 2군 감독 (다음 뉴스 ─ 전체기사 ─ 스포츠)","contents":"뉴스1<span class=\"txt_bar\"> · </span><span class=\"info_time\">05:14</span>","link":"https://v.daum.net/v/20230215051414436","retrieved":1676406030329},{"title":"KT 위즈로 이적한 김상수 (다음 뉴스 ─ 전체기사 ─ 스포츠)","contents":"뉴스1<span class=\"txt_bar\"> · </span><span class=\"info_time\">05:13</span>","link":"https://v.daum.net/v/20230215051357432","retrieved":1676406030330},{"title":"가볍게 몸 푸는 소형준 (다음 뉴스 ─ 전체기사 ─ 스포츠)","contents":"뉴스1<span class=\"txt_bar\"> · </span><span class=\"info_time\">05:13</span>","link":"https://v.daum.net/v/20230215051352431","retrieved":1676406030338},{"title":"훈련하는 KT 소형준 (다음 뉴스 ─ 전체기사 ─ 스포츠)","contents":"뉴스1<span class=\"txt_bar\"> · </span><span class=\"info_time\">05:13</span>","link":"https://v.daum.net/v/20230215051350430","retrieved":1676406030339},{"title":"[MD포토] 양현종 '깔끔한 투구폼' (다음 뉴스 ─ 전체기사 ─ 스포츠)","contents":"마이데일리<span class=\"txt_bar\"> · </span><span class=\"info_time\">05:13</span>","link":"https://v.daum.net/v/20230215051326428","retrieved":1676406030340},{"title":"‘빅 매치’ 제네시스 인비테이셔널 관전 포인트 (다음 뉴스 ─ 전체기사 ─ 스포츠)","contents":"아시아경제<span class=\"txt_bar\"> · </span><span class=\"info_time\">05:12</span>","link":"https://v.daum.net/v/20230215051248422","retrieved":1676406030341},{"title":"PAKISTAN CRICKET (다음 뉴스 ─ 전체기사 ─ 스포츠)","contents":"연합뉴스<span class=\"txt_bar\"> · </span><span class=\"info_time\">05:12</span>","link":"https://v.daum.net/v/20230215051221421","retrieved":1676406030343},{"title":"나성범, '힘차게' [사진] (다음 뉴스 ─ 전체기사 ─ 스포츠)","contents":"OSEN<span class=\"txt_bar\"> · </span><span class=\"info_time\">05:12</span>","link":"https://v.daum.net/v/20230215051207419","retrieved":1676406030344},{"title":"'국대 전문 킬러 출격' SSG WBC 3인방, 비장하게 애리조나 입성[플로리다 리포트] (다음 뉴스 ─ 전체기사 ─ 스포츠)","contents":"스포츠조선<span class=\"txt_bar\"> · </span><span class=\"info_time\">05:11</span>","link":"https://v.daum.net/v/20230215051115405","retrieved":1676406030346},{"title":"무에타이 승률 20%→韓최초 UFC 플라이… 박현성 “비결은” (다음 뉴스 ─ 전체기사 ─ 스포츠)","contents":"국민일보<span class=\"txt_bar\"> · </span><span class=\"info_time\">05:09</span>","link":"https://v.daum.net/v/20230215050915369","retrieved":1676406030348},{"title":"'인터넷의 아버지' 서프 \"챗봇 AI 서둘러 투자 마라\" 조언 (다음 뉴스 ─ 전체기사 ─ IT)","contents":"SBS Biz<span class=\"txt_bar\"> · </span><span class=\"info_time\">05:12</span>","link":"https://v.daum.net/v/20230215051200418","retrieved":1676406045546},{"title":"‘피파4’ 항저우아시안게임 국대 선발 (다음 뉴스 ─ 전체기사 ─ IT)","contents":"서울신문<span class=\"txt_bar\"> · </span><span class=\"info_time\">05:03</span>","link":"https://v.daum.net/v/20230215050349288","retrieved":1676406045547},{"title":"넷마블 걸그룹 ‘메이브’ 카카오 연재 (다음 뉴스 ─ 전체기사 ─ IT)","contents":"서울신문<span class=\"txt_bar\"> · </span><span class=\"info_time\">05:03</span>","link":"https://v.daum.net/v/20230215050347287","retrieved":1676406045548},{"title":"스마일게이트 ‘카즈’ 이벤트 매치 개최 (다음 뉴스 ─ 전체기사 ─ IT)","contents":"서울신문<span class=\"txt_bar\"> · </span><span class=\"info_time\">05:03</span>","link":"https://v.daum.net/v/20230215050346285","retrieved":1676406045553},{"title":"“게이밍 머신 대장, 나야 나”… 프리미엄 노트북 ‘그래픽 대전’ (다음 뉴스 ─ 전체기사 ─ IT)","contents":"서울신문<span class=\"txt_bar\"> · </span><span class=\"info_time\">05:03</span>","link":"https://v.daum.net/v/20230215050344284","retrieved":1676406045554},{"title":"갤럭시 스튜디오에서 S23 체험 (다음 뉴스 ─ 전체기사 ─ IT)","contents":"서울신문<span class=\"txt_bar\"> · </span><span class=\"info_time\">05:03</span>","link":"https://v.daum.net/v/20230215050324263","retrieved":1676406045555},{"title":"‘챗GPT’가 불 지핀 \nAI반도체 개발 경쟁 (다음 뉴스 ─ 전체기사 ─ IT)","contents":"서울신문<span class=\"txt_bar\"> · </span><span class=\"info_time\">05:03</span>","link":"https://v.daum.net/v/20230215050322259","retrieved":1676406045558},{"title":"현대차 \"초개인화로 스마트 모빌리티 고객경험 제공\" (다음 뉴스 ─ 전체기사 ─ IT)","contents":"디지털타임스<span class=\"txt_bar\"> · </span><span class=\"info_time\">05:03</span>","link":"https://v.daum.net/v/20230215050309239","retrieved":1676406045560},{"title":"7400㎞ 떨어진 한반도 지하수 7㎝ 출렁였다 (다음 뉴스 ─ 전체기사 ─ IT)","contents":"서울신문<span class=\"txt_bar\"> · </span><span class=\"info_time\">05:02</span>","link":"https://v.daum.net/v/20230215050232183","retrieved":1676406045560},{"title":"지역현안 조기 해결·총선 승리전략 정비 집중 (다음 뉴스 ─ 전체기사 ─ IT)","contents":"강원도민일보<span class=\"txt_bar\"> · </span><span class=\"info_time\">05:01</span>","link":"https://v.daum.net/v/20230215050114111","retrieved":1676406045565},{"title":"美, 가상화폐 본격 규제… 바이낸스 스테이블 코인 발행 중단 (다음 뉴스 ─ 전체기사 ─ IT)","contents":"머니S<span class=\"txt_bar\"> · </span><span class=\"info_time\">05:01</span>","link":"https://v.daum.net/v/20230215050108103","retrieved":1676406045567},{"title":"[스마트경제 '똑(Talk) 기업'] 정부지원부터 건강관리까지 집으로 연결 ‘일상 업그레이드’ (다음 뉴스 ─ 전체기사 ─ IT)","contents":"강원도민일보<span class=\"txt_bar\"> · </span><span class=\"info_time\">05:00</span>","link":"https://v.daum.net/v/20230215050033060","retrieved":1676406045568},{"title":"태백국민체육센터 운영공백 우려 (다음 뉴스 ─ 전체기사 ─ IT)","contents":"강원도민일보<span class=\"txt_bar\"> · </span><span class=\"info_time\">05:00</span>","link":"https://v.daum.net/v/20230215050032055","retrieved":1676406045569},{"title":"T멤버십, 3000명 이상이 100만원 이상 혜택 받아… 빵집이 최고 (다음 뉴스 ─ 전체기사 ─ IT)","contents":"머니S<span class=\"txt_bar\"> · </span><span class=\"info_time\">04:31</span>","link":"https://v.daum.net/v/20230215043106784","retrieved":1676406045570},{"title":"챗GPT 놀라 AI 지원법 신속 추진… \"사실상 8부 능선 넘어\" (다음 뉴스 ─ 전체기사 ─ IT)","contents":"머니S<span class=\"txt_bar\"> · </span><span class=\"info_time\">04:21</span>","link":"https://v.daum.net/v/20230215042105749","retrieved":1676406045571},{"title":"[Kim Seong-kon] 'Where to?' Which path should we take? (다음 뉴스 ─ 전체기사 ─ 칼럼)","contents":"코리아헤럴드<span class=\"txt_bar\"> · </span><span class=\"info_time\">05:17</span>","link":"https://v.daum.net/v/20230215051725464","retrieved":1676406056117},{"title":"[Doyle McManus] Spy balloon deflates US-China detente (다음 뉴스 ─ 전체기사 ─ 칼럼)","contents":"코리아헤럴드<span class=\"txt_bar\"> · </span><span class=\"info_time\">05:14</span>","link":"https://v.daum.net/v/20230215051425437","retrieved":1676406056117},{"title":"[사설] 알고리즘 조작한 카카오택시의 불공정 (다음 뉴스 ─ 전체기사 ─ 칼럼)","contents":"서울신문<span class=\"txt_bar\"> · </span><span class=\"info_time\">05:04</span>","link":"https://v.daum.net/v/20230215050425312","retrieved":1676406056117},{"title":"[사설] 巨野 ‘쌍특검’ 강행으론 역풍만 부를 뿐이다 (다음 뉴스 ─ 전체기사 ─ 칼럼)","contents":"서울신문<span class=\"txt_bar\"> · </span><span class=\"info_time\">05:04</span>","link":"https://v.daum.net/v/20230215050423311","retrieved":1676406056117},{"title":"[길섶에서] 동상이몽/박현갑 논설위원 (다음 뉴스 ─ 전체기사 ─ 칼럼)","contents":"서울신문<span class=\"txt_bar\"> · </span><span class=\"info_time\">05:04</span>","link":"https://v.daum.net/v/20230215050422310","retrieved":1676406056119},{"title":"[사설] “이재명 대통령” 회유, 사실이라면 책임 물어야 (다음 뉴스 ─ 전체기사 ─ 칼럼)","contents":"서울신문<span class=\"txt_bar\"> · </span><span class=\"info_time\">05:04</span>","link":"https://v.daum.net/v/20230215050421309","retrieved":1676406056148},{"title":"[씨줄날줄] 마라도 고양이/서동철 논설위원 (다음 뉴스 ─ 전체기사 ─ 칼럼)","contents":"서울신문<span class=\"txt_bar\"> · </span><span class=\"info_time\">05:04</span>","link":"https://v.daum.net/v/20230215050419308","retrieved":1676406056151},{"title":"[황수정 칼럼] 문재인의 ‘무례’로 짓는 집/수석논설위원 (다음 뉴스 ─ 전체기사 ─ 칼럼)","contents":"서울신문<span class=\"txt_bar\"> · </span><span class=\"info_time\">05:04</span>","link":"https://v.daum.net/v/20230215050418307","retrieved":1676406056156},{"title":"[마감 후] 상대를 두렵게 하는 말/안석 정치부 차장 (다음 뉴스 ─ 전체기사 ─ 칼럼)","contents":"서울신문<span class=\"txt_bar\"> · </span><span class=\"info_time\">05:04</span>","link":"https://v.daum.net/v/20230215050416305","retrieved":1676406056156},{"title":"[김택규의 문화 잠망경] 언어라는 조국/번역가 (다음 뉴스 ─ 전체기사 ─ 칼럼)","contents":"서울신문<span class=\"txt_bar\"> · </span><span class=\"info_time\">05:04</span>","link":"https://v.daum.net/v/20230215050414304","retrieved":1676406056156},{"title":"[열린세상] 한국의 현재가 된 인도, 국가적 관심 필요하다/송경진 전 세계경제연구원장 (다음 뉴스 ─ 전체기사 ─ 칼럼)","contents":"서울신문<span class=\"txt_bar\"> · </span><span class=\"info_time\">05:04</span>","link":"https://v.daum.net/v/20230215050412303","retrieved":1676406056156},{"title":"[장준우의 푸드 오디세이] 바닷속 맛의 폭탄, 조개류를 제대로 만난다/셰프 겸 칼럼니스트 (다음 뉴스 ─ 전체기사 ─ 칼럼)","contents":"서울신문<span class=\"txt_bar\"> · </span><span class=\"info_time\">05:04</span>","link":"https://v.daum.net/v/20230215050409302","retrieved":1676406056156},{"title":"[자치광장] 갈등, 피하지 말고 관리하자/김길성 서울 중구청장 (다음 뉴스 ─ 전체기사 ─ 칼럼)","contents":"서울신문<span class=\"txt_bar\"> · </span><span class=\"info_time\">05:04</span>","link":"https://v.daum.net/v/20230215050407301","retrieved":1676406056156},{"title":"[이근후의 팔팔구구] 인생은 찰나 (다음 뉴스 ─ 전체기사 ─ 칼럼)","contents":"농민신문<span class=\"txt_bar\"> · </span><span class=\"info_time\">05:03</span>","link":"https://v.daum.net/v/20230215050329270","retrieved":1676406056156},{"title":"[문화 읽기] 다양한 영화의 매력 속으로 (다음 뉴스 ─ 전체기사 ─ 칼럼)","contents":"농민신문<span class=\"txt_bar\"> · </span><span class=\"info_time\">05:03</span>","link":"https://v.daum.net/v/20230215050326266","retrieved":1676406056156},{"title":"신선한 농축산물·쾌적한 쇼핑공간…연매출 150억 돌파 (다음 뉴스 ─ 전체기사 ─ 보도자료)","contents":"농민신문<span class=\"txt_bar\"> · </span><span class=\"info_time\">05:03</span>","link":"https://v.daum.net/v/20230215050323260","retrieved":1676406064272},{"title":"양구군 생활인구 유입 지역브랜드 개발 (다음 뉴스 ─ 전체기사 ─ 보도자료)","contents":"강원도민일보<span class=\"txt_bar\"> · </span><span class=\"info_time\">05:00</span>","link":"https://v.daum.net/v/20230215050047075","retrieved":1676406064275},{"title":"강원도민 골다공증 주의…5년간 22% 증가 (다음 뉴스 ─ 전체기사 ─ 보도자료)","contents":"강원도민일보<span class=\"txt_bar\"> · </span><span class=\"info_time\">05:00</span>","link":"https://v.daum.net/v/20230215050005977","retrieved":1676406064277}]}