{"title":"Combined feed","url":"https://factcheckr.github.io/daum_news/all.xml","elements":[{"title":"존림 삼바 대표 \"우리 경쟁력, 스피드와 인재양성서 나온다\" (다음 뉴스 ─ 전체기사 ─ 최신)","contents":"헤럴드경제<span class=\"txt_bar\"> · </span><span class=\"info_time\">15:22</span>","link":"https://v.daum.net/v/20220614152216081","retrieved":1655187747795},{"title":"\"소방영웅 자녀 장학금 100년간\"..소방청·KG그룹 협약 (다음 뉴스 ─ 전체기사 ─ 최신)","contents":"뉴시스<span class=\"txt_bar\"> · </span><span class=\"info_time\">15:22</span>","link":"https://v.daum.net/v/20220614152214080","retrieved":1655187747796},{"title":"울산서 차량 진입 방해한 화물연대 조합원 2명 체포 (다음 뉴스 ─ 전체기사 ─ 최신)","contents":"뉴스1<span class=\"txt_bar\"> · </span><span class=\"info_time\">15:22</span>","link":"https://v.daum.net/v/20220614152213079","retrieved":1655187747796},{"title":"전북 남원시, 농산물 우수관리(GAP) 인증 농가 확대 (다음 뉴스 ─ 전체기사 ─ 최신)","contents":"아이뉴스24<span class=\"txt_bar\"> · </span><span class=\"info_time\">15:22</span>","link":"https://v.daum.net/v/20220614152211078","retrieved":1655187747798},{"title":"브리트니 스피어스, 유산 아픔 딛고 12세연하 남친과 재혼[할리우드비하인드] (다음 뉴스 ─ 전체기사 ─ 최신)","contents":"뉴스엔<span class=\"txt_bar\"> · </span><span class=\"info_time\">15:22</span>","link":"https://v.daum.net/v/20220614152210077","retrieved":1655187747801},{"title":"'송강호 아들' 송준평, 아이유와 케미 美쳤다 (다음 뉴스 ─ 전체기사 ─ 최신)","contents":"머니S<span class=\"txt_bar\"> · </span><span class=\"info_time\">15:22</span>","link":"https://v.daum.net/v/20220614152210076","retrieved":1655187747803},{"title":"[TD포토] 유인수 '다정한 손인사' (다음 뉴스 ─ 전체기사 ─ 최신)","contents":"티브이데일리<span class=\"txt_bar\"> · </span><span class=\"info_time\">15:22</span>","link":"https://v.daum.net/v/20220614152208074","retrieved":1655187747803},{"title":"철강 항만하역 입찰담합 동방·CJ대한통운 등 6곳 과징금 65억원 (다음 뉴스 ─ 전체기사 ─ 최신)","contents":"MBC<span class=\"txt_bar\"> · </span><span class=\"info_time\">15:22</span>","link":"https://v.daum.net/v/20220614152208073","retrieved":1655187747810},{"title":"[TD포토] 유인수 '단정한 블랙 패션' (다음 뉴스 ─ 전체기사 ─ 최신)","contents":"티브이데일리<span class=\"txt_bar\"> · </span><span class=\"info_time\">15:22</span>","link":"https://v.daum.net/v/20220614152206072","retrieved":1655187747812},{"title":"40도 넘는 '찜통 더위' 이어져..미국·유럽 '기록적 폭염' (다음 뉴스 ─ 전체기사 ─ 최신)","contents":"JTBC<span class=\"txt_bar\"> · </span><span class=\"info_time\">15:22</span>","link":"https://v.daum.net/v/20220614152206071","retrieved":1655187747813},{"title":"한해 \"래퍼 뒤늦게 시작, 스무 살 넘어 갑자기 진로 변경\"(컬투쇼) (다음 뉴스 ─ 전체기사 ─ 최신)","contents":"뉴스엔<span class=\"txt_bar\"> · </span><span class=\"info_time\">15:22</span>","link":"https://v.daum.net/v/20220614152206070","retrieved":1655187747819},{"title":"국수본, 국방정보본부 등 압수수색..군 장비 수주 관련 (다음 뉴스 ─ 전체기사 ─ 최신)","contents":"KBS<span class=\"txt_bar\"> · </span><span class=\"info_time\">15:22</span>","link":"https://v.daum.net/v/20220614152204069","retrieved":1655187747821},{"title":"[뉴스메이커] 황선홍 (다음 뉴스 ─ 전체기사 ─ 최신)","contents":"연합뉴스TV<span class=\"txt_bar\"> · </span><span class=\"info_time\">15:22</span>","link":"https://v.daum.net/v/20220614152203068","retrieved":1655187747822},{"title":"Riot Games, Incheon Airport to create esports lounge (다음 뉴스 ─ 전체기사 ─ 최신)","contents":"코리아헤럴드<span class=\"txt_bar\"> · </span><span class=\"info_time\">15:22</span>","link":"https://v.daum.net/v/20220614152201067","retrieved":1655187747824},{"title":"구미시장 당선인 인수위 출범..시민 소통 창구 개설 (다음 뉴스 ─ 전체기사 ─ 최신)","contents":"연합뉴스<span class=\"txt_bar\"> · </span><span class=\"info_time\">15:22</span>","link":"https://v.daum.net/v/20220614152200066","retrieved":1655187747825},{"title":"서울의소리 \"文 사저 욕설집회 중단하라\"..尹 자택 앞 맞불집회 (다음 뉴스 ─ 전체기사 ─ 사회)","contents":"뉴스1<span class=\"txt_bar\"> · </span><span class=\"info_time\">15:22</span>","link":"https://v.daum.net/v/20220614152225085","retrieved":1655187756637},{"title":"'코로나 검사부터 처방까지'..경기도, 원스톱 진료기관 1157곳 운영 (다음 뉴스 ─ 전체기사 ─ 사회)","contents":"뉴시스<span class=\"txt_bar\"> · </span><span class=\"info_time\">15:22</span>","link":"https://v.daum.net/v/20220614152221083","retrieved":1655187756638},{"title":"\"소방영웅 자녀 장학금 100년간\"..소방청·KG그룹 협약 (다음 뉴스 ─ 전체기사 ─ 사회)","contents":"뉴시스<span class=\"txt_bar\"> · </span><span class=\"info_time\">15:22</span>","link":"https://v.daum.net/v/20220614152214080","retrieved":1655187756643},{"title":"울산서 차량 진입 방해한 화물연대 조합원 2명 체포 (다음 뉴스 ─ 전체기사 ─ 사회)","contents":"뉴스1<span class=\"txt_bar\"> · </span><span class=\"info_time\">15:22</span>","link":"https://v.daum.net/v/20220614152213079","retrieved":1655187756643},{"title":"전북 남원시, 농산물 우수관리(GAP) 인증 농가 확대 (다음 뉴스 ─ 전체기사 ─ 사회)","contents":"아이뉴스24<span class=\"txt_bar\"> · </span><span class=\"info_time\">15:22</span>","link":"https://v.daum.net/v/20220614152211078","retrieved":1655187756644},{"title":"국수본, 국방정보본부 등 압수수색..군 장비 수주 관련 (다음 뉴스 ─ 전체기사 ─ 사회)","contents":"KBS<span class=\"txt_bar\"> · </span><span class=\"info_time\">15:22</span>","link":"https://v.daum.net/v/20220614152204069","retrieved":1655187756645},{"title":"광주 보건환경연구원, 수질·토양 분석 숙련도 국제인증 (다음 뉴스 ─ 전체기사 ─ 사회)","contents":"연합뉴스<span class=\"txt_bar\"> · </span><span class=\"info_time\">15:21</span>","link":"https://v.daum.net/v/20220614152158064","retrieved":1655187756656},{"title":"'코로나 첫해' 자살률 소폭 줄었다..30대 이하에서는 증가 (다음 뉴스 ─ 전체기사 ─ 사회)","contents":"동아일보<span class=\"txt_bar\"> · </span><span class=\"info_time\">15:21</span>","link":"https://v.daum.net/v/20220614152148061","retrieved":1655187756660},{"title":"헌혈 7년간 50번..김해도개공 방창민 대리, 헌혈 유공장 '금장' (다음 뉴스 ─ 전체기사 ─ 사회)","contents":"뉴시스<span class=\"txt_bar\"> · </span><span class=\"info_time\">15:21</span>","link":"https://v.daum.net/v/20220614152142058","retrieved":1655187756660},{"title":"현대제철 명장연구회, 당진 청소년 대상 후원 활동 지속 (다음 뉴스 ─ 전체기사 ─ 사회)","contents":"뉴스1<span class=\"txt_bar\"> · </span><span class=\"info_time\">15:21</span>","link":"https://v.daum.net/v/20220614152133055","retrieved":1655187756660},{"title":"\"라이더에 불리한 거리 측정은 사기\" 배달의민족 운영사 고발 (다음 뉴스 ─ 전체기사 ─ 사회)","contents":"서울신문<span class=\"txt_bar\"> · </span><span class=\"info_time\">15:21</span>","link":"https://v.daum.net/v/20220614152106047","retrieved":1655187756660},{"title":"조광한 남양주시장 명예훼손한 전 비서에 벌금 500만원 선고..재판부 \"책임 회피하고 반성 안해\" (다음 뉴스 ─ 전체기사 ─ 사회)","contents":"서울신문<span class=\"txt_bar\"> · </span><span class=\"info_time\">15:21</span>","link":"https://v.daum.net/v/20220614152102040","retrieved":1655187756670},{"title":"부산, 코로나19 이후 인구 대비 저소득층 비율 증가 전국 최고치 (다음 뉴스 ─ 전체기사 ─ 사회)","contents":"노컷뉴스<span class=\"txt_bar\"> · </span><span class=\"info_time\">15:21</span>","link":"https://v.daum.net/v/20220614152101038","retrieved":1655187756670},{"title":"코로나 완치됐더니 이제는 폐렴?.. \"9월 재유행 전에 백신 맞아라\" (다음 뉴스 ─ 전체기사 ─ 사회)","contents":"머니투데이<span class=\"txt_bar\"> · </span><span class=\"info_time\">15:20</span>","link":"https://v.daum.net/v/20220614152056031","retrieved":1655187756670},{"title":"'문 전 대통령 수사 촉구' (다음 뉴스 ─ 전체기사 ─ 사회)","contents":"뉴스1<span class=\"txt_bar\"> · </span><span class=\"info_time\">15:20</span>","link":"https://v.daum.net/v/20220614152056030","retrieved":1655187756671},{"title":"구미시장 당선인 인수위 출범..시민 소통 창구 개설 (다음 뉴스 ─ 전체기사 ─ 정치)","contents":"연합뉴스<span class=\"txt_bar\"> · </span><span class=\"info_time\">15:22</span>","link":"https://v.daum.net/v/20220614152200066","retrieved":1655187765392},{"title":"발명의 날 기념사 하는 한덕수 총리 (다음 뉴스 ─ 전체기사 ─ 정치)","contents":"연합뉴스<span class=\"txt_bar\"> · </span><span class=\"info_time\">15:21</span>","link":"https://v.daum.net/v/20220614152137057","retrieved":1655187765393},{"title":"한미 외교장관, 北 핵실험시 신속·단호히 대응 (다음 뉴스 ─ 전체기사 ─ 정치)","contents":"파이낸셜뉴스<span class=\"txt_bar\"> · </span><span class=\"info_time\">15:21</span>","link":"https://v.daum.net/v/20220614152119052","retrieved":1655187765393},{"title":"블링컨 만난 박진 \"한일 지소미아 정상화\" 얘기한 까닭은? (다음 뉴스 ─ 전체기사 ─ 정치)","contents":"뉴스1<span class=\"txt_bar\"> · </span><span class=\"info_time\">15:20</span>","link":"https://v.daum.net/v/20220614152051028","retrieved":1655187765395},{"title":"길어지는 '국회 공백'..\"법사위 갖겠다\" 공방만 벌이는 與野 (다음 뉴스 ─ 전체기사 ─ 정치)","contents":"머니투데이<span class=\"txt_bar\"> · </span><span class=\"info_time\">15:20</span>","link":"https://v.daum.net/v/20220614152033024","retrieved":1655187765395},{"title":"\"규제 개혁이 곧 국가성장\".. 대통령 주재 '규제혁신전략회의' 만든다 (다음 뉴스 ─ 전체기사 ─ 정치)","contents":"한국일보<span class=\"txt_bar\"> · </span><span class=\"info_time\">15:20</span>","link":"https://v.daum.net/v/20220614152031022","retrieved":1655187765395},{"title":"발명의 날 기념사 하는 한덕수 총리 (다음 뉴스 ─ 전체기사 ─ 정치)","contents":"연합뉴스<span class=\"txt_bar\"> · </span><span class=\"info_time\">15:20</span>","link":"https://v.daum.net/v/20220614152020014","retrieved":1655187765405},{"title":"우상호 \"화물연대 파업 해결 위해 여야 지도부 4인 회동 제안\" (다음 뉴스 ─ 전체기사 ─ 정치)","contents":"조선비즈<span class=\"txt_bar\"> · </span><span class=\"info_time\">15:20</span>","link":"https://v.daum.net/v/20220614152010005","retrieved":1655187765407},{"title":"이준석 \"尹, 과거 비해 앞서가는 모습..여당도 혁신해야\" (다음 뉴스 ─ 전체기사 ─ 정치)","contents":"헤럴드경제<span class=\"txt_bar\"> · </span><span class=\"info_time\">15:19</span>","link":"https://v.daum.net/v/20220614151931978","retrieved":1655187765407},{"title":"\"원자력 분야 최적 파트너\"..韓美, 원전협력 잰걸음 (다음 뉴스 ─ 전체기사 ─ 정치)","contents":"서울경제<span class=\"txt_bar\"> · </span><span class=\"info_time\">15:19</span>","link":"https://v.daum.net/v/20220614151912963","retrieved":1655187765408},{"title":"北 매체, 한미연합해상훈련 등 \"남조선 호전광들 군사적 망동\" 비난 (다음 뉴스 ─ 전체기사 ─ 정치)","contents":"파이낸셜뉴스<span class=\"txt_bar\"> · </span><span class=\"info_time\">15:18</span>","link":"https://v.daum.net/v/20220614151841941","retrieved":1655187765409},{"title":"[포토] 민생우선실천단 주재하는 우상호 비대위원장 (다음 뉴스 ─ 전체기사 ─ 정치)","contents":"아시아경제<span class=\"txt_bar\"> · </span><span class=\"info_time\">15:17</span>","link":"https://v.daum.net/v/20220614151712884","retrieved":1655187765410},{"title":"김민석 \"세대교체론 동의 안해..문제는 실력이다\" (다음 뉴스 ─ 전체기사 ─ 정치)","contents":"뉴스1<span class=\"txt_bar\"> · </span><span class=\"info_time\">15:16</span>","link":"https://v.daum.net/v/20220614151654870","retrieved":1655187765411},{"title":"[포토] 이야기 나누는 우상호-박홍근 (다음 뉴스 ─ 전체기사 ─ 정치)","contents":"아시아경제<span class=\"txt_bar\"> · </span><span class=\"info_time\">15:16</span>","link":"https://v.daum.net/v/20220614151653869","retrieved":1655187765412},{"title":"[포토] 민주당, 민생우선실천단 출범 (다음 뉴스 ─ 전체기사 ─ 정치)","contents":"아시아경제<span class=\"txt_bar\"> · </span><span class=\"info_time\">15:16</span>","link":"https://v.daum.net/v/20220614151638859","retrieved":1655187765414},{"title":"LG, AI 교육 프로그램 '에이머스' 출범..연간 4000명 양성 (다음 뉴스 ─ 전체기사 ─ 경제)","contents":"국민일보<span class=\"txt_bar\"> · </span><span class=\"info_time\">15:22</span>","link":"https://v.daum.net/v/20220614152246093","retrieved":1655187775241},{"title":"중기중앙회, 환경부 장관에 \"화평·화관법 등 중기 환경 규제 해소해 달라\" (다음 뉴스 ─ 전체기사 ─ 경제)","contents":"아시아경제<span class=\"txt_bar\"> · </span><span class=\"info_time\">15:22</span>","link":"https://v.daum.net/v/20220614152233089","retrieved":1655187775243},{"title":"Yoon vows supply-side efforts to tame inflation (다음 뉴스 ─ 전체기사 ─ 경제)","contents":"코리아헤럴드<span class=\"txt_bar\"> · </span><span class=\"info_time\">15:22</span>","link":"https://v.daum.net/v/20220614152224084","retrieved":1655187775244},{"title":"존림 삼바 대표 \"우리 경쟁력, 스피드와 인재양성서 나온다\" (다음 뉴스 ─ 전체기사 ─ 경제)","contents":"헤럴드경제<span class=\"txt_bar\"> · </span><span class=\"info_time\">15:22</span>","link":"https://v.daum.net/v/20220614152216081","retrieved":1655187775245},{"title":"철강 항만하역 입찰담합 동방·CJ대한통운 등 6곳 과징금 65억원 (다음 뉴스 ─ 전체기사 ─ 경제)","contents":"MBC<span class=\"txt_bar\"> · </span><span class=\"info_time\">15:22</span>","link":"https://v.daum.net/v/20220614152208073","retrieved":1655187775247},{"title":"8일째 맞는 화물연대 총파업..건설현장 공사 차질 (다음 뉴스 ─ 전체기사 ─ 경제)","contents":"연합뉴스<span class=\"txt_bar\"> · </span><span class=\"info_time\">15:21</span>","link":"https://v.daum.net/v/20220614152151063","retrieved":1655187775247},{"title":"원희룡 \"국가 경제 볼모로 일방적 요구..불법에 엄정 대응\" (다음 뉴스 ─ 전체기사 ─ 경제)","contents":"뉴시스<span class=\"txt_bar\"> · </span><span class=\"info_time\">15:21</span>","link":"https://v.daum.net/v/20220614152145059","retrieved":1655187775248},{"title":"영화 '범죄도시3' 투자 공모, 5억 규모..흥행성과로 배당 (다음 뉴스 ─ 전체기사 ─ 경제)","contents":"뉴시스<span class=\"txt_bar\"> · </span><span class=\"info_time\">15:21</span>","link":"https://v.daum.net/v/20220614152136056","retrieved":1655187775249},{"title":"이복현 금감원장 \"외환·단기금융 리스크부터 철저 점검\" (다음 뉴스 ─ 전체기사 ─ 경제)","contents":"비즈니스워치<span class=\"txt_bar\"> · </span><span class=\"info_time\">15:21</span>","link":"https://v.daum.net/v/20220614152105045","retrieved":1655187775250},{"title":"한솔홈데코, 긁힘·찍힘에 강한 섬유판 강마루 'sb마루' (다음 뉴스 ─ 전체기사 ─ 경제)","contents":"한국경제<span class=\"txt_bar\"> · </span><span class=\"info_time\">15:21</span>","link":"https://v.daum.net/v/20220614152104043","retrieved":1655187775252},{"title":"SK이노, 美 암모니아 연료전지 기업에 3천만달러 투자 (다음 뉴스 ─ 전체기사 ─ 경제)","contents":"쿠키뉴스<span class=\"txt_bar\"> · </span><span class=\"info_time\">15:21</span>","link":"https://v.daum.net/v/20220614152101039","retrieved":1655187775252},{"title":"우리카드, \"아이유 배경화면 다운받고 100만꿀도 받으세요\" (다음 뉴스 ─ 전체기사 ─ 경제)","contents":"파이낸셜뉴스<span class=\"txt_bar\"> · </span><span class=\"info_time\">15:20</span>","link":"https://v.daum.net/v/20220614152029021","retrieved":1655187775252},{"title":"엔바이오니아, 도레이첨단소재와 제휴..전기차 시장 겨냥 (다음 뉴스 ─ 전체기사 ─ 경제)","contents":"이데일리<span class=\"txt_bar\"> · </span><span class=\"info_time\">15:20</span>","link":"https://v.daum.net/v/20220614152023016","retrieved":1655187775253},{"title":"LX하우시스, 고단열 창호, 고품질 키친·바스..프리미엄 브랜드 자리매김 (다음 뉴스 ─ 전체기사 ─ 경제)","contents":"한국경제<span class=\"txt_bar\"> · </span><span class=\"info_time\">15:20</span>","link":"https://v.daum.net/v/20220614152002000","retrieved":1655187775254},{"title":"화물연대 총파업 8일째 피해 전방위 확산..건설현장 공사 차질 (다음 뉴스 ─ 전체기사 ─ 경제)","contents":"연합뉴스<span class=\"txt_bar\"> · </span><span class=\"info_time\">15:19</span>","link":"https://v.daum.net/v/20220614151958999","retrieved":1655187775256},{"title":"40도 넘는 '찜통 더위' 이어져..미국·유럽 '기록적 폭염' (다음 뉴스 ─ 전체기사 ─ 국제)","contents":"JTBC<span class=\"txt_bar\"> · </span><span class=\"info_time\">15:22</span>","link":"https://v.daum.net/v/20220614152206071","retrieved":1655187783592},{"title":"Riot Games, Incheon Airport to create esports lounge (다음 뉴스 ─ 전체기사 ─ 국제)","contents":"코리아헤럴드<span class=\"txt_bar\"> · </span><span class=\"info_time\">15:22</span>","link":"https://v.daum.net/v/20220614152201067","retrieved":1655187783594},{"title":"기후변화에 우크라전 덮친 식량 위기..4900만명 기근 직면 (다음 뉴스 ─ 전체기사 ─ 국제)","contents":"뉴시스<span class=\"txt_bar\"> · </span><span class=\"info_time\">15:20</span>","link":"https://v.daum.net/v/20220614152024017","retrieved":1655187783596},{"title":"中, 대만과의 군사행동 대비하나 (다음 뉴스 ─ 전체기사 ─ 국제)","contents":"서울경제<span class=\"txt_bar\"> · </span><span class=\"info_time\">15:20</span>","link":"https://v.daum.net/v/20220614152019013","retrieved":1655187783604},{"title":"스웨덴 103세 할머니 '세계 최고령 스카이다이버' 등극 (다음 뉴스 ─ 전체기사 ─ 국제)","contents":"이데일리<span class=\"txt_bar\"> · </span><span class=\"info_time\">15:19</span>","link":"https://v.daum.net/v/20220614151919970","retrieved":1655187783607},{"title":"요즘 감기 환자 많던데..코로나19가 바이러스 유행 시기도 바꿨다 (다음 뉴스 ─ 전체기사 ─ 국제)","contents":"뉴시스<span class=\"txt_bar\"> · </span><span class=\"info_time\">15:18</span>","link":"https://v.daum.net/v/20220614151856952","retrieved":1655187783609},{"title":"'자이언트 스텝도 약해'..일각서 100bp 관측도 (다음 뉴스 ─ 전체기사 ─ 국제)","contents":"채널A<span class=\"txt_bar\"> · </span><span class=\"info_time\">15:18</span>","link":"https://v.daum.net/v/20220614151847948","retrieved":1655187783613},{"title":"'美 1·6 의회 폭동' 청문회 증인으로 나온 한국계 前연방검사 (다음 뉴스 ─ 전체기사 ─ 국제)","contents":"연합뉴스<span class=\"txt_bar\"> · </span><span class=\"info_time\">15:18</span>","link":"https://v.daum.net/v/20220614151827934","retrieved":1655187783615},{"title":"'지소미아 정상화' 언급에.. \"평화에 기여\" 환영한 일본 (다음 뉴스 ─ 전체기사 ─ 국제)","contents":"오마이뉴스<span class=\"txt_bar\"> · </span><span class=\"info_time\">15:18</span>","link":"https://v.daum.net/v/20220614151809919","retrieved":1655187783617},{"title":"총기협회 'A+' 의원이 나섰다..美 총기 규제법 이번엔 통과? (다음 뉴스 ─ 전체기사 ─ 국제)","contents":"머니투데이<span class=\"txt_bar\"> · </span><span class=\"info_time\">15:17</span>","link":"https://v.daum.net/v/20220614151730894","retrieved":1655187783619},{"title":"세계증시 약세장 진입, 11월 이후 시총 18조달러 증발(상보) (다음 뉴스 ─ 전체기사 ─ 국제)","contents":"뉴스1<span class=\"txt_bar\"> · </span><span class=\"info_time\">15:16</span>","link":"https://v.daum.net/v/20220614151635858","retrieved":1655187783620},{"title":"아프간 전직 고관들, 호화판 해외생활..일반인 '경제난 극심'과 대비 (다음 뉴스 ─ 전체기사 ─ 국제)","contents":"한겨레<span class=\"txt_bar\"> · </span><span class=\"info_time\">15:15</span>","link":"https://v.daum.net/v/20220614151506806","retrieved":1655187783622},{"title":"중국군 해외파병 근거..시진핑 '비전쟁 군사행동 요강' 서명 (다음 뉴스 ─ 전체기사 ─ 국제)","contents":"SBS<span class=\"txt_bar\"> · </span><span class=\"info_time\">15:15</span>","link":"https://v.daum.net/v/20220614151500791","retrieved":1655187783623},{"title":"배우 김민규 '묘해, 당신의 미술관'전으로 고양이 작품 공개 (다음 뉴스 ─ 전체기사 ─ 국제)","contents":"MBN<span class=\"txt_bar\"> · </span><span class=\"info_time\">15:14</span>","link":"https://v.daum.net/v/20220614151433771","retrieved":1655187783624},{"title":"골대 앞 오두방정..호주 '댄싱 골키퍼' 작전 통했다 (영상) (다음 뉴스 ─ 전체기사 ─ 국제)","contents":"동아일보<span class=\"txt_bar\"> · </span><span class=\"info_time\">15:13</span>","link":"https://v.daum.net/v/20220614151305717","retrieved":1655187783625},{"title":"이영훈 여의도순복음교회 목사, \"北 260개군에 인민병원 설립\" (다음 뉴스 ─ 전체기사 ─ 문화)","contents":"서울경제<span class=\"txt_bar\"> · </span><span class=\"info_time\">15:22</span>","link":"https://v.daum.net/v/20220614152253102","retrieved":1655187791668},{"title":"4년 새 췌장암 환자 29.4%↑.. 조기발견 힘든 이유는? (다음 뉴스 ─ 전체기사 ─ 문화)","contents":"머니S<span class=\"txt_bar\"> · </span><span class=\"info_time\">15:22</span>","link":"https://v.daum.net/v/20220614152250099","retrieved":1655187791675},{"title":"[날씨] 곳곳에 강풍과 함께 빗방울..15일도 흐림 (다음 뉴스 ─ 전체기사 ─ 문화)","contents":"JTBC<span class=\"txt_bar\"> · </span><span class=\"info_time\">15:21</span>","link":"https://v.daum.net/v/20220614152110050","retrieved":1655187791675},{"title":"'파친코' 배우 김민하 따라 합천 해인사 오세요 (다음 뉴스 ─ 전체기사 ─ 문화)","contents":"매일경제<span class=\"txt_bar\"> · </span><span class=\"info_time\">15:21</span>","link":"https://v.daum.net/v/20220614152106046","retrieved":1655187791676},{"title":"오물·곰팡이 뒤섞인 10평 아파트에 고양이 13마리 방치 (다음 뉴스 ─ 전체기사 ─ 문화)","contents":"연합뉴스<span class=\"txt_bar\"> · </span><span class=\"info_time\">15:21</span>","link":"https://v.daum.net/v/20220614152104044","retrieved":1655187791677},{"title":"유치원 학부모 서류제출 불편 줄인다..교육정보망 개통 (다음 뉴스 ─ 전체기사 ─ 문화)","contents":"키즈맘<span class=\"txt_bar\"> · </span><span class=\"info_time\">15:21</span>","link":"https://v.daum.net/v/20220614152102041","retrieved":1655187791678},{"title":"유일한 원숭이두창 치료제 테코비리마트 국내 도입 추진 (다음 뉴스 ─ 전체기사 ─ 문화)","contents":"동아사이언스<span class=\"txt_bar\"> · </span><span class=\"info_time\">15:20</span>","link":"https://v.daum.net/v/20220614152018011","retrieved":1655187791678},{"title":"코로나19 신규 치료제 개발 중단 우려 커져..임상참가자 모집 '난항' (다음 뉴스 ─ 전체기사 ─ 문화)","contents":"동아사이언스<span class=\"txt_bar\"> · </span><span class=\"info_time\">15:20</span>","link":"https://v.daum.net/v/20220614152012009","retrieved":1655187791679},{"title":"\"오세훈 시장님, 서울대공원 침팬지 해외 반출 막아주세요\" (다음 뉴스 ─ 전체기사 ─ 문화)","contents":"한국일보<span class=\"txt_bar\"> · </span><span class=\"info_time\">15:20</span>","link":"https://v.daum.net/v/20220614152011007","retrieved":1655187791681},{"title":"[르포]5성급 HMR 맛은..'워커힐 고메' 밀키트 먹어보니 (다음 뉴스 ─ 전체기사 ─ 문화)","contents":"이데일리<span class=\"txt_bar\"> · </span><span class=\"info_time\">15:20</span>","link":"https://v.daum.net/v/20220614152008003","retrieved":1655187791682},{"title":"정읍시 작은 도서관 5곳 '책 체험 버스' 운영 (다음 뉴스 ─ 전체기사 ─ 문화)","contents":"연합뉴스<span class=\"txt_bar\"> · </span><span class=\"info_time\">15:19</span>","link":"https://v.daum.net/v/20220614151955997","retrieved":1655187791684},{"title":"호식이두마리치킨, 배달의민족 4000원 할인 이벤트 진행 (다음 뉴스 ─ 전체기사 ─ 문화)","contents":"베이비뉴스<span class=\"txt_bar\"> · </span><span class=\"info_time\">15:18</span>","link":"https://v.daum.net/v/20220614151830935","retrieved":1655187791684},{"title":"아울북-tvN '벌거벗은 세계사', 어린이를 위한 세계사 입문 도서 출간 (다음 뉴스 ─ 전체기사 ─ 문화)","contents":"베이비뉴스<span class=\"txt_bar\"> · </span><span class=\"info_time\">15:17</span>","link":"https://v.daum.net/v/20220614151749903","retrieved":1655187791685},{"title":"폴 포츠, 데뷔 15주년 내한 콘서트..22∼23일 서울서 (다음 뉴스 ─ 전체기사 ─ 문화)","contents":"연합뉴스<span class=\"txt_bar\"> · </span><span class=\"info_time\">15:17</span>","link":"https://v.daum.net/v/20220614151704879","retrieved":1655187791686},{"title":"원숭이두창 고위험접촉자 21일 격리..내달 두창 치료제 500회분 도입 추진 (다음 뉴스 ─ 전체기사 ─ 문화)","contents":"서울경제<span class=\"txt_bar\"> · </span><span class=\"info_time\">15:16</span>","link":"https://v.daum.net/v/20220614151646866","retrieved":1655187791687},{"title":"'이필립♥︎' 박현선, 베일에 싸였던 2세 공개..고사리같은 손 \"사랑스러워\" (다음 뉴스 ─ 전체기사 ─ 연예)","contents":"OSEN<span class=\"txt_bar\"> · </span><span class=\"info_time\">15:23</span>","link":"https://v.daum.net/v/20220614152307112","retrieved":1655187800687},{"title":"돈스파이크 \"강남·이상화 양쪽 축의금 냈는데 내 결혼식 안와..쓰레기\" (다음 뉴스 ─ 전체기사 ─ 연예)","contents":"뉴스1<span class=\"txt_bar\"> · </span><span class=\"info_time\">15:23</span>","link":"https://v.daum.net/v/20220614152307111","retrieved":1655187800691},{"title":"'링크' 김찬형, 여진구와의 과거 인연 밝혀졌다..궁금증 유발 (다음 뉴스 ─ 전체기사 ─ 연예)","contents":"OSEN<span class=\"txt_bar\"> · </span><span class=\"info_time\">15:22</span>","link":"https://v.daum.net/v/20220614152249097","retrieved":1655187800691},{"title":"\"즐거운 축제 만들 것\"..제26회 BIFAN, 관객과 직접 만난다[스경X현장] (다음 뉴스 ─ 전체기사 ─ 연예)","contents":"스포츠경향<span class=\"txt_bar\"> · </span><span class=\"info_time\">15:22</span>","link":"https://v.daum.net/v/20220614152244092","retrieved":1655187800691},{"title":"[단독] 장나라, 6세 연하 남친과 6월26일 오후 서울 모처서 비공개 결혼식 (다음 뉴스 ─ 전체기사 ─ 연예)","contents":"뉴스1<span class=\"txt_bar\"> · </span><span class=\"info_time\">15:22</span>","link":"https://v.daum.net/v/20220614152219082","retrieved":1655187800691},{"title":"브리트니 스피어스, 유산 아픔 딛고 12세연하 남친과 재혼[할리우드비하인드] (다음 뉴스 ─ 전체기사 ─ 연예)","contents":"뉴스엔<span class=\"txt_bar\"> · </span><span class=\"info_time\">15:22</span>","link":"https://v.daum.net/v/20220614152210077","retrieved":1655187800691},{"title":"'송강호 아들' 송준평, 아이유와 케미 美쳤다 (다음 뉴스 ─ 전체기사 ─ 연예)","contents":"머니S<span class=\"txt_bar\"> · </span><span class=\"info_time\">15:22</span>","link":"https://v.daum.net/v/20220614152210076","retrieved":1655187800691},{"title":"[TD포토] 유인수 '다정한 손인사' (다음 뉴스 ─ 전체기사 ─ 연예)","contents":"티브이데일리<span class=\"txt_bar\"> · </span><span class=\"info_time\">15:22</span>","link":"https://v.daum.net/v/20220614152208074","retrieved":1655187800691},{"title":"[TD포토] 유인수 '단정한 블랙 패션' (다음 뉴스 ─ 전체기사 ─ 연예)","contents":"티브이데일리<span class=\"txt_bar\"> · </span><span class=\"info_time\">15:22</span>","link":"https://v.daum.net/v/20220614152206072","retrieved":1655187800693},{"title":"한해 \"래퍼 뒤늦게 시작, 스무 살 넘어 갑자기 진로 변경\"(컬투쇼) (다음 뉴스 ─ 전체기사 ─ 연예)","contents":"뉴스엔<span class=\"txt_bar\"> · </span><span class=\"info_time\">15:22</span>","link":"https://v.daum.net/v/20220614152206070","retrieved":1655187800694},{"title":"공효진, ♥10살 연하 케빈오에 오빠라 해도 될 듯..더 어려졌어 (다음 뉴스 ─ 전체기사 ─ 연예)","contents":"뉴스엔<span class=\"txt_bar\"> · </span><span class=\"info_time\">15:21</span>","link":"https://v.daum.net/v/20220614152148060","retrieved":1655187800694},{"title":"'윤남기♥' 이다은, 귀여운 딸 근황 공개..미소 병아리 [리포트:컷] (다음 뉴스 ─ 전체기사 ─ 연예)","contents":"TV리포트<span class=\"txt_bar\"> · </span><span class=\"info_time\">15:21</span>","link":"https://v.daum.net/v/20220614152131054","retrieved":1655187800695},{"title":"현아가 포착한 ♥던 흡연..사랑해도 금연은 안 권하나봐 (다음 뉴스 ─ 전체기사 ─ 연예)","contents":"OSEN<span class=\"txt_bar\"> · </span><span class=\"info_time\">15:21</span>","link":"https://v.daum.net/v/20220614152123053","retrieved":1655187800697},{"title":"\"성장의 즐거움 느낄 것\" '환혼' 이재욱·정소민 뭉친 '판타지 활극'(종합) (다음 뉴스 ─ 전체기사 ─ 연예)","contents":"뉴스1<span class=\"txt_bar\"> · </span><span class=\"info_time\">15:21</span>","link":"https://v.daum.net/v/20220614152107049","retrieved":1655187800698},{"title":"'환혼' 이재욱 \"출연 이유? 박준화 감독 '나만 믿고 따라오라'고\" (다음 뉴스 ─ 전체기사 ─ 연예)","contents":"스타투데이<span class=\"txt_bar\"> · </span><span class=\"info_time\">15:21</span>","link":"https://v.daum.net/v/20220614152102042","retrieved":1655187800700},{"title":"대한세팍타크로협회, 미스터피자와 후원 협약 체결 (다음 뉴스 ─ 전체기사 ─ 스포츠)","contents":"연합뉴스<span class=\"txt_bar\"> · </span><span class=\"info_time\">15:23</span>","link":"https://v.daum.net/v/20220614152305110","retrieved":1655187809898},{"title":"'케인 감독님' 못 보려나? \"은퇴 후에 골프선수 할 수도\" (다음 뉴스 ─ 전체기사 ─ 스포츠)","contents":"마이데일리<span class=\"txt_bar\"> · </span><span class=\"info_time\">15:23</span>","link":"https://v.daum.net/v/20220614152302105","retrieved":1655187809899},{"title":"[뉴스메이커] 황선홍 (다음 뉴스 ─ 전체기사 ─ 스포츠)","contents":"연합뉴스TV<span class=\"txt_bar\"> · </span><span class=\"info_time\">15:22</span>","link":"https://v.daum.net/v/20220614152203068","retrieved":1655187809899},{"title":"버버리도 인정한 월드클래스, \"SON과 함께 해 자랑스러워\" (다음 뉴스 ─ 전체기사 ─ 스포츠)","contents":"스포탈코리아<span class=\"txt_bar\"> · </span><span class=\"info_time\">15:21</span>","link":"https://v.daum.net/v/20220614152159065","retrieved":1655187809900},{"title":"'디펜딩'이태훈vs'2연승' 신상훈, 하나은행 인비테이셔널서 격돌 (다음 뉴스 ─ 전체기사 ─ 스포츠)","contents":"파이낸셜뉴스<span class=\"txt_bar\"> · </span><span class=\"info_time\">15:21</span>","link":"https://v.daum.net/v/20220614152148062","retrieved":1655187809901},{"title":"최고 권위 '내셔널 타이틀 대회' 한국여자오픈 골프 모레 개막 (다음 뉴스 ─ 전체기사 ─ 스포츠)","contents":"SBS<span class=\"txt_bar\"> · </span><span class=\"info_time\">15:21</span>","link":"https://v.daum.net/v/20220614152100035","retrieved":1655187809902},{"title":"스포츠키다 \"한국, 오늘밤 이집트에 2대0 승리 예상\" (다음 뉴스 ─ 전체기사 ─ 스포츠)","contents":"국민일보<span class=\"txt_bar\"> · </span><span class=\"info_time\">15:20</span>","link":"https://v.daum.net/v/20220614152044027","retrieved":1655187809904},{"title":"프로축구선수협 '월드컵 20주년 기념' 연말 자선축구 추진. \"팬들에게 감동 전하겠다\" (다음 뉴스 ─ 전체기사 ─ 스포츠)","contents":"스포츠조선<span class=\"txt_bar\"> · </span><span class=\"info_time\">15:20</span>","link":"https://v.daum.net/v/20220614152029020","retrieved":1655187809904},{"title":"'SON 짝꿍', 미래 '프로 골퍼' 꿈꾼다..\"불가능이란 없다!\" (다음 뉴스 ─ 전체기사 ─ 스포츠)","contents":"OSEN<span class=\"txt_bar\"> · </span><span class=\"info_time\">15:17</span>","link":"https://v.daum.net/v/20220614151723890","retrieved":1655187809906},{"title":"벤투호 상대 포르투갈·우루과이 왜 이리 잘하지..호날두·카바니 펄펄 (다음 뉴스 ─ 전체기사 ─ 스포츠)","contents":"중앙일보<span class=\"txt_bar\"> · </span><span class=\"info_time\">15:17</span>","link":"https://v.daum.net/v/20220614151700874","retrieved":1655187809907},{"title":"'신기술 돌핀킥-포프 코치 칭찬'에 자신감 상승 황선우 \"세계선수권 시상대 오르겠다\" (다음 뉴스 ─ 전체기사 ─ 스포츠)","contents":"스포티비뉴스<span class=\"txt_bar\"> · </span><span class=\"info_time\">15:16</span>","link":"https://v.daum.net/v/20220614151653868","retrieved":1655187809909},{"title":"박은선 7년 만에 대표팀 복귀..여자축구 27일 캐나다와 원정 평가전 (다음 뉴스 ─ 전체기사 ─ 스포츠)","contents":"스포츠동아<span class=\"txt_bar\"> · </span><span class=\"info_time\">15:16</span>","link":"https://v.daum.net/v/20220614151642862","retrieved":1655187809910},{"title":"일본 프로야구 다카쓰 감독, 야쿠르트와 2년 연장 계약 (다음 뉴스 ─ 전체기사 ─ 스포츠)","contents":"연합뉴스<span class=\"txt_bar\"> · </span><span class=\"info_time\">15:16</span>","link":"https://v.daum.net/v/20220614151612848","retrieved":1655187809911},{"title":"위긴스 26득점·13리바운드 맹활약..커리는 외롭지 않았다 (다음 뉴스 ─ 전체기사 ─ 스포츠)","contents":"서울신문<span class=\"txt_bar\"> · </span><span class=\"info_time\">15:16</span>","link":"https://v.daum.net/v/20220614151601835","retrieved":1655187809912},{"title":"김하성, 4경기 만에 안타..타율 0.212 (다음 뉴스 ─ 전체기사 ─ 스포츠)","contents":"서울경제<span class=\"txt_bar\"> · </span><span class=\"info_time\">15:15</span>","link":"https://v.daum.net/v/20220614151531822","retrieved":1655187809914},{"title":"에스씨지솔루션즈, 대전 지사 출범 충청·호남지역 사업 강화 (다음 뉴스 ─ 전체기사 ─ IT)","contents":"지디넷코리아<span class=\"txt_bar\"> · </span><span class=\"info_time\">15:23</span>","link":"https://v.daum.net/v/20220614152322119","retrieved":1655187818274},{"title":"위메이드·밸로프, 위믹스 플랫폼에 C9·뮤 레전드 연동 (다음 뉴스 ─ 전체기사 ─ IT)","contents":"연합뉴스<span class=\"txt_bar\"> · </span><span class=\"info_time\">15:23</span>","link":"https://v.daum.net/v/20220614152314114","retrieved":1655187818276},{"title":"펄어비스, 검은사막 모바일 '2022 하이델 연회' 7월 2일 개최 (다음 뉴스 ─ 전체기사 ─ IT)","contents":"게임톡<span class=\"txt_bar\"> · </span><span class=\"info_time\">15:22</span>","link":"https://v.daum.net/v/20220614152235091","retrieved":1655187818279},{"title":"\"삼성에 돈 안받았다\"..Z플립 42만번 여닫고 흙탕물 뿌려도 멀쩡 (다음 뉴스 ─ 전체기사 ─ IT)","contents":"조선일보<span class=\"txt_bar\"> · </span><span class=\"info_time\">15:22</span>","link":"https://v.daum.net/v/20220614152228087","retrieved":1655187818279},{"title":"센스톤, KDB산업은행에서 50억원 신규투자 유치 (다음 뉴스 ─ 전체기사 ─ IT)","contents":"지디넷코리아<span class=\"txt_bar\"> · </span><span class=\"info_time\">15:20</span>","link":"https://v.daum.net/v/20220614152057032","retrieved":1655187818280},{"title":"박형준 \"디지털 기업 부산 유치 노력\"..경영정보 춘계통합학술대회 막 내려 (다음 뉴스 ─ 전체기사 ─ IT)","contents":"전자신문<span class=\"txt_bar\"> · </span><span class=\"info_time\">15:20</span>","link":"https://v.daum.net/v/20220614152008004","retrieved":1655187818283},{"title":"'NFT-블록체인 게임 컨퍼런스'서 컴투스홀딩스 C2X 방향성 공개 (다음 뉴스 ─ 전체기사 ─ IT)","contents":"게임동아<span class=\"txt_bar\"> · </span><span class=\"info_time\">15:18</span>","link":"https://v.daum.net/v/20220614151804913","retrieved":1655187818287},{"title":"[리뷰] 화제의 '디아블로 이모탈' 만렙까지 즐겨봤습니다 (다음 뉴스 ─ 전체기사 ─ IT)","contents":"게임톡<span class=\"txt_bar\"> · </span><span class=\"info_time\">15:17</span>","link":"https://v.daum.net/v/20220614151709881","retrieved":1655187818287},{"title":"[올쇼TV] \"프로젝트 일정관리/해석데이터 관리\" 6월 21일 웨비나 생방송 (다음 뉴스 ─ 전체기사 ─ IT)","contents":"전자신문<span class=\"txt_bar\"> · </span><span class=\"info_time\">15:17</span>","link":"https://v.daum.net/v/20220614151707880","retrieved":1655187818288},{"title":"'SAP 나우 서울' 콘퍼런스..삼성SDS·LG CNS 등 참가 (다음 뉴스 ─ 전체기사 ─ IT)","contents":"연합뉴스<span class=\"txt_bar\"> · </span><span class=\"info_time\">15:16</span>","link":"https://v.daum.net/v/20220614151658873","retrieved":1655187818288},{"title":"이호근 대덕대 교수 \"아이오닉5 부산 화재사고, 운전자 과실\" (다음 뉴스 ─ 전체기사 ─ IT)","contents":"디지털타임스<span class=\"txt_bar\"> · </span><span class=\"info_time\">15:15</span>","link":"https://v.daum.net/v/20220614151506807","retrieved":1655187818290},{"title":"거리두기 풀리자..'영화·외식 앱' 이용 늘고 '배달 앱' 이용 줄었다 (다음 뉴스 ─ 전체기사 ─ IT)","contents":"뉴스1<span class=\"txt_bar\"> · </span><span class=\"info_time\">15:15</span>","link":"https://v.daum.net/v/20220614151504801","retrieved":1655187818290},{"title":"그램퍼스 '마이리틀셰프', 오뚜기 온라인 쇼핑몰 게임 내 구현 (다음 뉴스 ─ 전체기사 ─ IT)","contents":"지디넷코리아<span class=\"txt_bar\"> · </span><span class=\"info_time\">15:14</span>","link":"https://v.daum.net/v/20220614151427766","retrieved":1655187818291},{"title":"국내 4대 거래소, 스테이블코인 가격 불안정에 '트론' 투자 주의보 (다음 뉴스 ─ 전체기사 ─ IT)","contents":"뉴스1<span class=\"txt_bar\"> · </span><span class=\"info_time\">15:14</span>","link":"https://v.daum.net/v/20220614151424762","retrieved":1655187818294},{"title":"아이피샵, 한국가요작가협회와 MOU..'음원프로젝트 다각화' 등 엔터허브 본격화 (다음 뉴스 ─ 전체기사 ─ IT)","contents":"전자신문<span class=\"txt_bar\"> · </span><span class=\"info_time\">15:13</span>","link":"https://v.daum.net/v/20220614151302715","retrieved":1655187818296},{"title":"원희룡 \"국민경제 볼모로 파업 이어가면 중대 결단\" (다음 뉴스 ─ 전체기사 ─ 칼럼)","contents":"한국경제TV<span class=\"txt_bar\"> · </span><span class=\"info_time\">14:48</span>","link":"https://v.daum.net/v/20220614144820577","retrieved":1655187827085},{"title":"[투자의 창] 오래 전 기사가 투자 내공을 키운다 (다음 뉴스 ─ 전체기사 ─ 칼럼)","contents":"서울경제<span class=\"txt_bar\"> · </span><span class=\"info_time\">14:06</span>","link":"https://v.daum.net/v/20220614140630926","retrieved":1655184698653},{"title":"[ET시론]K-콘텐츠와 IT 그리고 '크리에이티브 코리아' (다음 뉴스 ─ 전체기사 ─ 칼럼)","contents":"전자신문<span class=\"txt_bar\"> · </span><span class=\"info_time\">14:01</span>","link":"https://v.daum.net/v/20220614140102696","retrieved":1655184698653},{"title":"[의학칼럼]윗몸일으키기 대신 '이 운동' 해보세요 (다음 뉴스 ─ 전체기사 ─ 칼럼)","contents":"헬스조선<span class=\"txt_bar\"> · </span><span class=\"info_time\">14:00</span>","link":"https://v.daum.net/v/20220614140018661","retrieved":1655184698654},{"title":"[유레카] 한덕수, 김진표 그리고 차별금지법/ 신윤동욱 (다음 뉴스 ─ 전체기사 ─ 칼럼)","contents":"한겨레<span class=\"txt_bar\"> · </span><span class=\"info_time\">14:00</span>","link":"https://v.daum.net/v/20220614140008641","retrieved":1655184698655},{"title":"'전세푸어' 쏟아지는데, 하반기 전세난 없다고?[부동산360] (다음 뉴스 ─ 전체기사 ─ 칼럼)","contents":"헤럴드경제<span class=\"txt_bar\"> · </span><span class=\"info_time\">12:26</span>","link":"https://v.daum.net/v/20220614122639493","retrieved":1655178808264},{"title":"[WORD_ON_THE_WEB] 'What are the president and the government doing?' (다음 뉴스 ─ 전체기사 ─ 칼럼)","contents":"코리아중앙데일리<span class=\"txt_bar\"> · </span><span class=\"info_time\">12:19</span>","link":"https://v.daum.net/v/20220614121947369","retrieved":1655178808265},{"title":"[WORD_ON_THE_WEB] 'It's only fair to receive punishment for one's crimes' (다음 뉴스 ─ 전체기사 ─ 칼럼)","contents":"코리아중앙데일리<span class=\"txt_bar\"> · </span><span class=\"info_time\">12:17</span>","link":"https://v.daum.net/v/20220614121738330","retrieved":1655178808267},{"title":"<사설>국내외 다중위기 급속 악화..尹정부 '경제 역량' 보일 때 (다음 뉴스 ─ 전체기사 ─ 칼럼)","contents":"문화일보<span class=\"txt_bar\"> · </span><span class=\"info_time\">12:05</span>","link":"https://v.daum.net/v/20220614120534101","retrieved":1655178808268},{"title":"<사설>'文정부 블랙리스트' 백운규 영장, 靑 수사 본격화해야 (다음 뉴스 ─ 전체기사 ─ 칼럼)","contents":"문화일보<span class=\"txt_bar\"> · </span><span class=\"info_time\">12:05</span>","link":"https://v.daum.net/v/20220614120534100","retrieved":1655178808269},{"title":"<사설>학력 미달 중고생 5년간 2배, 시험·숙제부터 되살리라 (다음 뉴스 ─ 전체기사 ─ 칼럼)","contents":"문화일보<span class=\"txt_bar\"> · </span><span class=\"info_time\">12:05</span>","link":"https://v.daum.net/v/20220614120533098","retrieved":1655178808269},{"title":"<포럼>민주당 '시행령 통제法'의 위헌 우려 (다음 뉴스 ─ 전체기사 ─ 칼럼)","contents":"문화일보<span class=\"txt_bar\"> · </span><span class=\"info_time\">12:05</span>","link":"https://v.daum.net/v/20220614120531095","retrieved":1655178808270},{"title":"<포럼>지역별 특화 필요한 반도체 인재 전략 (다음 뉴스 ─ 전체기사 ─ 칼럼)","contents":"문화일보<span class=\"txt_bar\"> · </span><span class=\"info_time\">12:01</span>","link":"https://v.daum.net/v/20220614120112902","retrieved":1655178808270},{"title":"[기고] 마케팅 성공을 좌우할 데이터 전략 (다음 뉴스 ─ 전체기사 ─ 칼럼)","contents":"아이뉴스24<span class=\"txt_bar\"> · </span><span class=\"info_time\">12:00</span>","link":"https://v.daum.net/v/20220614120041817","retrieved":1655178808271},{"title":"<시평>북핵 대응 '전담 조직' 필요하다 (다음 뉴스 ─ 전체기사 ─ 칼럼)","contents":"문화일보<span class=\"txt_bar\"> · </span><span class=\"info_time\">11:56</span>","link":"https://v.daum.net/v/20220614115603652","retrieved":1655178808271},{"title":"강원도 시멘트산업 탄소중립 실증 본격 추진 (다음 뉴스 ─ 전체기사 ─ 보도자료)","contents":"중앙일보<span class=\"txt_bar\"> · </span><span class=\"info_time\">15:20</span>","link":"https://v.daum.net/v/20220614152031023","retrieved":1655187835674},{"title":"여름꽃향기 피어나는 거창창포원 (다음 뉴스 ─ 전체기사 ─ 보도자료)","contents":"연합뉴스 보도자료<span class=\"txt_bar\"> · </span><span class=\"info_time\">15:19</span>","link":"https://v.daum.net/v/20220614151945986","retrieved":1655187835678},{"title":"남양주시 다산1동, 재사용의류 리폼 사업 실시 (다음 뉴스 ─ 전체기사 ─ 보도자료)","contents":"연합뉴스 보도자료<span class=\"txt_bar\"> · </span><span class=\"info_time\">15:19</span>","link":"https://v.daum.net/v/20220614151927974","retrieved":1655187835681},{"title":"에스피에스엔에이, 다회용 컵 사용 문화 확산 '앞장' (다음 뉴스 ─ 전체기사 ─ 보도자료)","contents":"중앙일보<span class=\"txt_bar\"> · </span><span class=\"info_time\">15:19</span>","link":"https://v.daum.net/v/20220614151920972","retrieved":1655187835682},{"title":"광명시 핸드볼팀 SK슈가글라이더즈, 10주년 행사 및 팬미팅 (다음 뉴스 ─ 전체기사 ─ 보도자료)","contents":"연합뉴스 보도자료<span class=\"txt_bar\"> · </span><span class=\"info_time\">15:19</span>","link":"https://v.daum.net/v/20220614151911962","retrieved":1655187835689},{"title":"평택시, 2022년 가뭄 극복 종합대책 보고회 개최 (다음 뉴스 ─ 전체기사 ─ 보도자료)","contents":"연합뉴스 보도자료<span class=\"txt_bar\"> · </span><span class=\"info_time\">15:18</span>","link":"https://v.daum.net/v/20220614151852951","retrieved":1655187835690},{"title":"목포시, 목포미식문화갤러리 선보인다 (다음 뉴스 ─ 전체기사 ─ 보도자료)","contents":"연합뉴스 보도자료<span class=\"txt_bar\"> · </span><span class=\"info_time\">15:18</span>","link":"https://v.daum.net/v/20220614151832936","retrieved":1655187835690},{"title":"해운대 아틀리에 칙칙폭폭, '모래작품 NFT 전' 개최 (다음 뉴스 ─ 전체기사 ─ 보도자료)","contents":"연합뉴스 보도자료<span class=\"txt_bar\"> · </span><span class=\"info_time\">15:18</span>","link":"https://v.daum.net/v/20220614151813923","retrieved":1655187835690},{"title":"고려대학교 세종캠퍼스, 한국연구재단 주관 '2022년 박사과정생 연구장려금 지원사업'에 3명 선정 (다음 뉴스 ─ 전체기사 ─ 보도자료)","contents":"중앙일보<span class=\"txt_bar\"> · </span><span class=\"info_time\">15:18</span>","link":"https://v.daum.net/v/20220614151800909","retrieved":1655187835690},{"title":"전남도, 국산 김치 소비 촉진 활성화 박차 (다음 뉴스 ─ 전체기사 ─ 보도자료)","contents":"연합뉴스 보도자료<span class=\"txt_bar\"> · </span><span class=\"info_time\">15:17</span>","link":"https://v.daum.net/v/20220614151742898","retrieved":1655187835692},{"title":"민주주의자 예춘호의 정치를 돌아본다 (다음 뉴스 ─ 전체기사 ─ 보도자료)","contents":"중앙일보<span class=\"txt_bar\"> · </span><span class=\"info_time\">15:16</span>","link":"https://v.daum.net/v/20220614151620852","retrieved":1655187835693},{"title":"산림사업장 안전사고 예방을 위한 교육 및 특별점검 (다음 뉴스 ─ 전체기사 ─ 보도자료)","contents":"정책브리핑<span class=\"txt_bar\"> · </span><span class=\"info_time\">15:06</span>","link":"https://v.daum.net/v/20220614150607421","retrieved":1655187835694},{"title":"2022년 임업직불금 신청대상 및 신청기간 변경 알림 (다음 뉴스 ─ 전체기사 ─ 보도자료)","contents":"정책브리핑<span class=\"txt_bar\"> · </span><span class=\"info_time\">15:05</span>","link":"https://v.daum.net/v/20220614150559405","retrieved":1655187835695},{"title":"(참고) 중소기업중앙회와 실시간 소통 구축..규제개혁 협력 (다음 뉴스 ─ 전체기사 ─ 보도자료)","contents":"정책브리핑<span class=\"txt_bar\"> · </span><span class=\"info_time\">15:05</span>","link":"https://v.daum.net/v/20220614150556402","retrieved":1655187835696},{"title":"부총리 주재 「부동산 시장 관련 전문가 간담회」 개최 (다음 뉴스 ─ 전체기사 ─ 보도자료)","contents":"정책브리핑<span class=\"txt_bar\"> · </span><span class=\"info_time\">15:05</span>","link":"https://v.daum.net/v/20220614150556401","retrieved":1655187835697},{"title":"부산 동부리 기장한신그린코아아파트 59㎡ 2억4000만원.. 역대 최고가 (다음 뉴스 ─ 전체기사 ─ 자동생성기사)","contents":"조선비즈<span class=\"txt_bar\"> · </span><span class=\"info_time\">14:20</span>","link":"https://v.daum.net/v/20220614142057446","retrieved":1655184715815},{"title":"서울 답십리동 래미안미드카운티 123㎡ 18억3000만원.. 역대 최고가 (다음 뉴스 ─ 전체기사 ─ 자동생성기사)","contents":"조선비즈<span class=\"txt_bar\"> · </span><span class=\"info_time\">14:15</span>","link":"https://v.daum.net/v/20220614141558269","retrieved":1655184715816},{"title":"부산 거제동 유림아시아드아파트 146㎡ 6억8500만원.. 역대 최고가 (다음 뉴스 ─ 전체기사 ─ 자동생성기사)","contents":"조선비즈<span class=\"txt_bar\"> · </span><span class=\"info_time\">14:10</span>","link":"https://v.daum.net/v/20220614141057081","retrieved":1655184715817},{"title":"부산 만덕동 만덕그린코아아파트 134㎡ 2억9500만원.. 역대 최고가 (다음 뉴스 ─ 전체기사 ─ 자동생성기사)","contents":"조선비즈<span class=\"txt_bar\"> · </span><span class=\"info_time\">14:06</span>","link":"https://v.daum.net/v/20220614140605900","retrieved":1655184715818},{"title":"서울 이문동 이문쌍용 59㎡ 8억4700만원.. 역대 최고가 (다음 뉴스 ─ 전체기사 ─ 자동생성기사)","contents":"조선비즈<span class=\"txt_bar\"> · </span><span class=\"info_time\">14:01</span>","link":"https://v.daum.net/v/20220614140105701","retrieved":1655184715819},{"title":"용인 보라동 민속마을쌍용 139㎡ 5억5000만원에 거래 (다음 뉴스 ─ 전체기사 ─ 자동생성기사)","contents":"조선비즈<span class=\"txt_bar\"> · </span><span class=\"info_time\">13:56</span>","link":"https://v.daum.net/v/20220614135603522","retrieved":1655184715819},{"title":"인천 만수동 만수 주공4단지 아파트 75㎡ 4억원에 거래 (다음 뉴스 ─ 전체기사 ─ 자동생성기사)","contents":"조선비즈<span class=\"txt_bar\"> · </span><span class=\"info_time\">13:50</span>","link":"https://v.daum.net/v/20220614135059351","retrieved":1655182426663},{"title":"인천 만수동 만수주공2단지아파트 47㎡ 2억8000만원에 거래 (다음 뉴스 ─ 전체기사 ─ 자동생성기사)","contents":"조선비즈<span class=\"txt_bar\"> · </span><span class=\"info_time\">13:45</span>","link":"https://v.daum.net/v/20220614134556210","retrieved":1655182426664},{"title":"하남 망월동 미사강변스타힐스 59㎡ 8억6000만원에 거래 (다음 뉴스 ─ 전체기사 ─ 자동생성기사)","contents":"조선비즈<span class=\"txt_bar\"> · </span><span class=\"info_time\">13:41</span>","link":"https://v.daum.net/v/20220614134101039","retrieved":1655182426667},{"title":"수원 영통동 영통벽적골롯데 59㎡ 5억5300만원에 거래 (다음 뉴스 ─ 전체기사 ─ 자동생성기사)","contents":"조선비즈<span class=\"txt_bar\"> · </span><span class=\"info_time\">13:36</span>","link":"https://v.daum.net/v/20220614133600839","retrieved":1655182426668},{"title":"용인 상갈동 금화마을주공3단지 59㎡ 5억4500만원에 거래 (다음 뉴스 ─ 전체기사 ─ 자동생성기사)","contents":"조선비즈<span class=\"txt_bar\"> · </span><span class=\"info_time\">13:30</span>","link":"https://v.daum.net/v/20220614133056677","retrieved":1655182426668},{"title":"수원 영통동 영통황골주공1차 59㎡ 4억9500만원에 거래 (다음 뉴스 ─ 전체기사 ─ 자동생성기사)","contents":"조선비즈<span class=\"txt_bar\"> · </span><span class=\"info_time\">13:25</span>","link":"https://v.daum.net/v/20220614132558475","retrieved":1655182426670},{"title":"수원 정자동 정자동신2차 69㎡ 4억3500만원에 거래 (다음 뉴스 ─ 전체기사 ─ 자동생성기사)","contents":"조선비즈<span class=\"txt_bar\"> · </span><span class=\"info_time\">13:21</span>","link":"https://v.daum.net/v/20220614132102309","retrieved":1655182426676},{"title":"수원 영통동 영통청명마을벽산삼익 73㎡ 6억2000만원에 거래 (다음 뉴스 ─ 전체기사 ─ 자동생성기사)","contents":"조선비즈<span class=\"txt_bar\"> · </span><span class=\"info_time\">13:15</span>","link":"https://v.daum.net/v/20220614131556129","retrieved":1655182426677},{"title":"성남 창곡동 위례호반베르디움  98㎡ 14억9500만원에 거래 (다음 뉴스 ─ 전체기사 ─ 자동생성기사)","contents":"조선비즈<span class=\"txt_bar\"> · </span><span class=\"info_time\">13:11</span>","link":"https://v.daum.net/v/20220614131102022","retrieved":1655182426679}]}