{"title":"Combined feed","url":"https://factcheckr.github.io/daum_news/all.xml","elements":[{"title":"[4·10 총선] '컷오프 반발' 현역 이채익 첫 탈당…개혁신당은 안 간다 (다음 뉴스 ─ 전체기사 ─ 최신)","contents":"MBN<span class=\"txt_bar\"> · </span><span class=\"info_time\">19:14</span>","link":"https://v.daum.net/v/20240306191429518","retrieved":1709720087086},{"title":"尹 \"법과 원칙에 따라 엄정 대응...'전문의 중심' 병원으로\" (다음 뉴스 ─ 전체기사 ─ 최신)","contents":"YTN<span class=\"txt_bar\"> · </span><span class=\"info_time\">19:14</span>","link":"https://v.daum.net/v/20240306191424517","retrieved":1709720087086},{"title":"Vatican Pope (다음 뉴스 ─ 전체기사 ─ 최신)","contents":"연합뉴스<span class=\"txt_bar\"> · </span><span class=\"info_time\">19:14</span>","link":"https://v.daum.net/v/20240306191419516","retrieved":1709720087087},{"title":"Drone Show Korea 2024 kicks off in Busan (다음 뉴스 ─ 전체기사 ─ 최신)","contents":"코리아중앙데일리<span class=\"txt_bar\"> · </span><span class=\"info_time\">19:14</span>","link":"https://v.daum.net/v/20240306191412515","retrieved":1709720087087},{"title":"구자은 “LS이링크 연내 상장 추진” (다음 뉴스 ─ 전체기사 ─ 최신)","contents":"서울신문<span class=\"txt_bar\"> · </span><span class=\"info_time\">19:14</span>","link":"https://v.daum.net/v/20240306191402514","retrieved":1709720087090},{"title":"이준석 “경기 남부 8∼10명 배치… 치열한 경쟁 펼칠 것” [총선열전] (다음 뉴스 ─ 전체기사 ─ 최신)","contents":"세계일보<span class=\"txt_bar\"> · </span><span class=\"info_time\">19:13</span>","link":"https://v.daum.net/v/20240306191359513","retrieved":1709720087091},{"title":"피치, 한국 신용등급 'AA-' 유지…등급전망 '안정적'(상보) (다음 뉴스 ─ 전체기사 ─ 최신)","contents":"머니투데이<span class=\"txt_bar\"> · </span><span class=\"info_time\">19:13</span>","link":"https://v.daum.net/v/20240306191356512","retrieved":1709720087092},{"title":"한 명 구속, 다른 한 명 ‘총선’ 때문에 사임…SPC 공동 대표 둘 다 없다 (다음 뉴스 ─ 전체기사 ─ 최신)","contents":"한국일보<span class=\"txt_bar\"> · </span><span class=\"info_time\">19:13</span>","link":"https://v.daum.net/v/20240306191336511","retrieved":1709720087094},{"title":"의대 정원 배분 본격화… 교수들 반발 확산 [‘의료대란’ 비상] (다음 뉴스 ─ 전체기사 ─ 최신)","contents":"세계일보<span class=\"txt_bar\"> · </span><span class=\"info_time\">19:13</span>","link":"https://v.daum.net/v/20240306191321510","retrieved":1709720087098},{"title":"‘내시경 실습하실 분’… 전공의 돕기 나선 선배 의사들 [‘의료대란’ 비상] (다음 뉴스 ─ 전체기사 ─ 최신)","contents":"세계일보<span class=\"txt_bar\"> · </span><span class=\"info_time\">19:13</span>","link":"https://v.daum.net/v/20240306191319509","retrieved":1709720087098},{"title":"블랙핑크, '러브식 걸즈' 안무 영상 3억뷰 (다음 뉴스 ─ 전체기사 ─ 최신)","contents":"이데일리<span class=\"txt_bar\"> · </span><span class=\"info_time\">19:13</span>","link":"https://v.daum.net/v/20240306191318508","retrieved":1709720087101},{"title":"의대 교수들, 정부 상대로 증원 취소소송 제기… 쟁점은? [‘의료대란’ 비상] (다음 뉴스 ─ 전체기사 ─ 최신)","contents":"세계일보<span class=\"txt_bar\"> · </span><span class=\"info_time\">19:13</span>","link":"https://v.daum.net/v/20240306191318507","retrieved":1709720087102},{"title":"KLPGA 투어 시즌 대장정 돌입… 박지영, 개막전 '타이틀 방어' 도전 (다음 뉴스 ─ 전체기사 ─ 최신)","contents":"머니S<span class=\"txt_bar\"> · </span><span class=\"info_time\">19:13</span>","link":"https://v.daum.net/v/20240306191311505","retrieved":1709720087103},{"title":"다목적 소방헬기 도입한 인천소방본부 [포토뉴스] (다음 뉴스 ─ 전체기사 ─ 최신)","contents":"경기일보<span class=\"txt_bar\"> · </span><span class=\"info_time\">19:13</span>","link":"https://v.daum.net/v/20240306191305504","retrieved":1709720087105},{"title":"서사 없는 사회의 ‘안티히어로’ (다음 뉴스 ─ 전체기사 ─ 최신)","contents":"한겨레21<span class=\"txt_bar\"> · </span><span class=\"info_time\">19:13</span>","link":"https://v.daum.net/v/20240306191301503","retrieved":1709720087106},{"title":"의대 정원 배분 본격화… 교수들 반발 확산 [‘의료대란’ 비상] (다음 뉴스 ─ 전체기사 ─ 사회)","contents":"세계일보<span class=\"txt_bar\"> · </span><span class=\"info_time\">19:13</span>","link":"https://v.daum.net/v/20240306191321510","retrieved":1709720095841},{"title":"‘내시경 실습하실 분’… 전공의 돕기 나선 선배 의사들 [‘의료대란’ 비상] (다음 뉴스 ─ 전체기사 ─ 사회)","contents":"세계일보<span class=\"txt_bar\"> · </span><span class=\"info_time\">19:13</span>","link":"https://v.daum.net/v/20240306191319509","retrieved":1709720095841},{"title":"의대 교수들, 정부 상대로 증원 취소소송 제기… 쟁점은? [‘의료대란’ 비상] (다음 뉴스 ─ 전체기사 ─ 사회)","contents":"세계일보<span class=\"txt_bar\"> · </span><span class=\"info_time\">19:13</span>","link":"https://v.daum.net/v/20240306191318507","retrieved":1709720095843},{"title":"서사 없는 사회의 ‘안티히어로’ (다음 뉴스 ─ 전체기사 ─ 사회)","contents":"한겨레21<span class=\"txt_bar\"> · </span><span class=\"info_time\">19:13</span>","link":"https://v.daum.net/v/20240306191301503","retrieved":1709720095843},{"title":"조희대 대법원장, 다음주부터 두달간 법원 현장 방문 (다음 뉴스 ─ 전체기사 ─ 사회)","contents":"뉴스1<span class=\"txt_bar\"> · </span><span class=\"info_time\">19:12</span>","link":"https://v.daum.net/v/20240306191246500","retrieved":1709720095843},{"title":"[자막뉴스] '한계 임박' 의료현장, 비상진료  돌입 (다음 뉴스 ─ 전체기사 ─ 사회)","contents":"JIBS<span class=\"txt_bar\"> · </span><span class=\"info_time\">19:12</span>","link":"https://v.daum.net/v/20240306191245499","retrieved":1709720095849},{"title":"함은정, 교통사고 가해자에 커피 준 이유…\"내 차 아니었다\" (다음 뉴스 ─ 전체기사 ─ 사회)","contents":"머니투데이<span class=\"txt_bar\"> · </span><span class=\"info_time\">19:12</span>","link":"https://v.daum.net/v/20240306191217493","retrieved":1709720095849},{"title":"경북 포항 쌀, 아프리카 밥상 오른다…나이지리아 최초 수출 (다음 뉴스 ─ 전체기사 ─ 사회)","contents":"농민신문<span class=\"txt_bar\"> · </span><span class=\"info_time\">19:12</span>","link":"https://v.daum.net/v/20240306191215492","retrieved":1709720095850},{"title":"화성에서 온수 배관 파열돼 도로 연기...차량 정체 (다음 뉴스 ─ 전체기사 ─ 사회)","contents":"YTN<span class=\"txt_bar\"> · </span><span class=\"info_time\">19:12</span>","link":"https://v.daum.net/v/20240306191201486","retrieved":1709720095850},{"title":"“30초만에 7000만원 털렸다”…헬멧 쓴 금은방 절도범, 오토바이 타고 도주 (다음 뉴스 ─ 전체기사 ─ 사회)","contents":"매일경제<span class=\"txt_bar\"> · </span><span class=\"info_time\">19:12</span>","link":"https://v.daum.net/v/20240306191200485","retrieved":1709720095851},{"title":"의협 간부 첫 소환 “사직 교사 안했다”…제약회사 직원 동원 의혹도 수사 (다음 뉴스 ─ 전체기사 ─ 사회)","contents":"KBS<span class=\"txt_bar\"> · </span><span class=\"info_time\">19:11</span>","link":"https://v.daum.net/v/20240306191150481","retrieved":1709720095852},{"title":"충북지식재산센터, 지식재산 창업존 교육생 모집 (다음 뉴스 ─ 전체기사 ─ 사회)","contents":"CJB청주방송<span class=\"txt_bar\"> · </span><span class=\"info_time\">19:11</span>","link":"https://v.daum.net/v/20240306191143479","retrieved":1709720095853},{"title":"김포 상가에 차량 돌진…“운전미숙 추정, 인명피해 없어” (다음 뉴스 ─ 전체기사 ─ 사회)","contents":"KBS<span class=\"txt_bar\"> · </span><span class=\"info_time\">19:11</span>","link":"https://v.daum.net/v/20240306191133478","retrieved":1709720095855},{"title":"송영길 \"실형 받은 조국도 창당, 나는 활동 못 하나\" (다음 뉴스 ─ 전체기사 ─ 사회)","contents":"아시아경제<span class=\"txt_bar\"> · </span><span class=\"info_time\">19:10</span>","link":"https://v.daum.net/v/20240306191019475","retrieved":1709720095856},{"title":"의협 집행부 첫 경찰 소환...\"MZ 전공의 자발적 행동\" (다음 뉴스 ─ 전체기사 ─ 사회)","contents":"YTN<span class=\"txt_bar\"> · </span><span class=\"info_time\">19:10</span>","link":"https://v.daum.net/v/20240306191014473","retrieved":1709720095857},{"title":"엇갈린 영입인재 행보…與 비례로 '우르르', 野 지역구 '도전' (다음 뉴스 ─ 전체기사 ─ 정치)","contents":"이데일리<span class=\"txt_bar\"> · </span><span class=\"info_time\">19:14</span>","link":"https://v.daum.net/v/20240306191448520","retrieved":1709720102829},{"title":"[4·10 총선] '컷오프 반발' 현역 이채익 첫 탈당…개혁신당은 안 간다 (다음 뉴스 ─ 전체기사 ─ 정치)","contents":"MBN<span class=\"txt_bar\"> · </span><span class=\"info_time\">19:14</span>","link":"https://v.daum.net/v/20240306191429518","retrieved":1709720102831},{"title":"尹 \"법과 원칙에 따라 엄정 대응...'전문의 중심' 병원으로\" (다음 뉴스 ─ 전체기사 ─ 정치)","contents":"YTN<span class=\"txt_bar\"> · </span><span class=\"info_time\">19:14</span>","link":"https://v.daum.net/v/20240306191424517","retrieved":1709720102832},{"title":"이준석 “경기 남부 8∼10명 배치… 치열한 경쟁 펼칠 것” [총선열전] (다음 뉴스 ─ 전체기사 ─ 정치)","contents":"세계일보<span class=\"txt_bar\"> · </span><span class=\"info_time\">19:13</span>","link":"https://v.daum.net/v/20240306191359513","retrieved":1709720102833},{"title":"방송사 테러한 北 침투부대 섬멸 작전…민관군 합동대응훈련 실시 (다음 뉴스 ─ 전체기사 ─ 정치)","contents":"채널A<span class=\"txt_bar\"> · </span><span class=\"info_time\">19:12</span>","link":"https://v.daum.net/v/20240306191251501","retrieved":1709720102834},{"title":"[4·10 공천] \"시스템 공천 깨져\" 텃밭 컷오프 홍석준·유경준 공개 반발 (다음 뉴스 ─ 전체기사 ─ 정치)","contents":"MBN<span class=\"txt_bar\"> · </span><span class=\"info_time\">19:12</span>","link":"https://v.daum.net/v/20240306191235496","retrieved":1709720102836},{"title":"[기획] 尹, 의사 반발에 `경고장` 날렸다 (다음 뉴스 ─ 전체기사 ─ 정치)","contents":"디지털타임스<span class=\"txt_bar\"> · </span><span class=\"info_time\">19:12</span>","link":"https://v.daum.net/v/20240306191230495","retrieved":1709720102839},{"title":"尹대통령, 국무회의 주재 (다음 뉴스 ─ 전체기사 ─ 정치)","contents":"세계일보<span class=\"txt_bar\"> · </span><span class=\"info_time\">19:12</span>","link":"https://v.daum.net/v/20240306191207490","retrieved":1709720102841},{"title":"[노컷브이]\"윤석열, '925조원 공수표 남발'…돈이 어디서 나오나\" (다음 뉴스 ─ 전체기사 ─ 정치)","contents":"노컷뉴스<span class=\"txt_bar\"> · </span><span class=\"info_time\">19:12</span>","link":"https://v.daum.net/v/20240306191207489","retrieved":1709720102843},{"title":"최관재 경기도선관위 사무처장 “국민 신뢰받는 공정한 선거 관리…위법 행위, 무관용 원칙” (다음 뉴스 ─ 전체기사 ─ 정치)","contents":"경기일보<span class=\"txt_bar\"> · </span><span class=\"info_time\">19:12</span>","link":"https://v.daum.net/v/20240306191205488","retrieved":1709720102844},{"title":"윤 대통령 “상급의료 정상화 과정”…조목조목 반박 (다음 뉴스 ─ 전체기사 ─ 정치)","contents":"KBS<span class=\"txt_bar\"> · </span><span class=\"info_time\">19:11</span>","link":"https://v.daum.net/v/20240306191153482","retrieved":1709720102846},{"title":"[뉴스추적] 더 벌어진 격차, 총선 민심은? (다음 뉴스 ─ 전체기사 ─ 정치)","contents":"MBN<span class=\"txt_bar\"> · </span><span class=\"info_time\">19:10</span>","link":"https://v.daum.net/v/20240306191031477","retrieved":1709720102847},{"title":"\"정치 학살\" \"원칙 깨져\"…공천 막판 파열음 (다음 뉴스 ─ 전체기사 ─ 정치)","contents":"연합뉴스TV<span class=\"txt_bar\"> · </span><span class=\"info_time\">19:10</span>","link":"https://v.daum.net/v/20240306191018474","retrieved":1709720102848},{"title":"[속보] 병무청장 “전공의 사직서 무더기 수리 땐 내년부터 순차 입대” (다음 뉴스 ─ 전체기사 ─ 정치)","contents":"문화일보<span class=\"txt_bar\"> · </span><span class=\"info_time\">19:09</span>","link":"https://v.daum.net/v/20240306190909463","retrieved":1709720102850},{"title":"당 지지도 국힘 39% vs 민주 32%…윤 대통령 지지율 5%p 올라 (다음 뉴스 ─ 전체기사 ─ 정치)","contents":"MBN<span class=\"txt_bar\"> · </span><span class=\"info_time\">19:08</span>","link":"https://v.daum.net/v/20240306190830456","retrieved":1709720102851},{"title":"'한미-OCI 통합' 법정 공방, 한미 주총전 결론 날 듯 (다음 뉴스 ─ 전체기사 ─ 경제)","contents":"연합뉴스<span class=\"txt_bar\"> · </span><span class=\"info_time\">19:14</span>","link":"https://v.daum.net/v/20240306191447519","retrieved":1709720111269},{"title":"Drone Show Korea 2024 kicks off in Busan (다음 뉴스 ─ 전체기사 ─ 경제)","contents":"코리아중앙데일리<span class=\"txt_bar\"> · </span><span class=\"info_time\">19:14</span>","link":"https://v.daum.net/v/20240306191412515","retrieved":1709720111271},{"title":"구자은 “LS이링크 연내 상장 추진” (다음 뉴스 ─ 전체기사 ─ 경제)","contents":"서울신문<span class=\"txt_bar\"> · </span><span class=\"info_time\">19:14</span>","link":"https://v.daum.net/v/20240306191402514","retrieved":1709720111277},{"title":"피치, 한국 신용등급 'AA-' 유지…등급전망 '안정적'(상보) (다음 뉴스 ─ 전체기사 ─ 경제)","contents":"머니투데이<span class=\"txt_bar\"> · </span><span class=\"info_time\">19:13</span>","link":"https://v.daum.net/v/20240306191356512","retrieved":1709720111277},{"title":"한 명 구속, 다른 한 명 ‘총선’ 때문에 사임…SPC 공동 대표 둘 다 없다 (다음 뉴스 ─ 전체기사 ─ 경제)","contents":"한국일보<span class=\"txt_bar\"> · </span><span class=\"info_time\">19:13</span>","link":"https://v.daum.net/v/20240306191336511","retrieved":1709720111277},{"title":"류동근 한국해양대 총장 취임…\"글로벌 대학 만들겠다\" (다음 뉴스 ─ 전체기사 ─ 경제)","contents":"연합뉴스<span class=\"txt_bar\"> · </span><span class=\"info_time\">19:13</span>","link":"https://v.daum.net/v/20240306191300502","retrieved":1709720111284},{"title":"사업 착수 하세월…안산산단 주민들·민간 사업자 한숨만 (다음 뉴스 ─ 전체기사 ─ 경제)","contents":"대전일보<span class=\"txt_bar\"> · </span><span class=\"info_time\">19:12</span>","link":"https://v.daum.net/v/20240306191225494","retrieved":1709720111284},{"title":"산모·신생아·소아 등에 1200억 건보 투입…필수의료 보상 강화 즉시 추진 (다음 뉴스 ─ 전체기사 ─ 경제)","contents":"머니투데이<span class=\"txt_bar\"> · </span><span class=\"info_time\">19:12</span>","link":"https://v.daum.net/v/20240306191214491","retrieved":1709720111286},{"title":"피치, 韓 국가신용등급 ‘AA-’ 유지…“연말 기준금리 3.0%”(상보) (다음 뉴스 ─ 전체기사 ─ 경제)","contents":"이데일리<span class=\"txt_bar\"> · </span><span class=\"info_time\">19:08</span>","link":"https://v.daum.net/v/20240306190855458","retrieved":1709720111286},{"title":"제2순환고속도로 등 미동 않는 '충청 교통망 구성' 총선으로 뚫어야 (다음 뉴스 ─ 전체기사 ─ 경제)","contents":"대전일보<span class=\"txt_bar\"> · </span><span class=\"info_time\">19:08</span>","link":"https://v.daum.net/v/20240306190818453","retrieved":1709720111288},{"title":"취업제한 소송 중인데···SK證, 박정림 사외이사 파격 내정 (다음 뉴스 ─ 전체기사 ─ 경제)","contents":"서울경제<span class=\"txt_bar\"> · </span><span class=\"info_time\">19:07</span>","link":"https://v.daum.net/v/20240306190727448","retrieved":1709720111289},{"title":"삼성SDI \"2027년 전고체 배터리 양산\" vs LG엔솔 \"완성도가 중요\" (다음 뉴스 ─ 전체기사 ─ 경제)","contents":"한국경제<span class=\"txt_bar\"> · </span><span class=\"info_time\">19:06</span>","link":"https://v.daum.net/v/20240306190602437","retrieved":1709720111290},{"title":"강선희 SPC 대표 1년만에 사임…남편 김진모 국힘 예비후보 선거 지원 (다음 뉴스 ─ 전체기사 ─ 경제)","contents":"매일경제<span class=\"txt_bar\"> · </span><span class=\"info_time\">19:06</span>","link":"https://v.daum.net/v/20240306190601436","retrieved":1709720111291},{"title":"15kg 車 부품도 가뿐…현대차 들썩이게 만들 일꾼의 정체 (다음 뉴스 ─ 전체기사 ─ 경제)","contents":"한국경제<span class=\"txt_bar\"> · </span><span class=\"info_time\">19:05</span>","link":"https://v.daum.net/v/20240306190502428","retrieved":1709720111291},{"title":"피치, 韓 신용등급 'AA-' 유지…등급전망도 '안정적' 유지 (다음 뉴스 ─ 전체기사 ─ 경제)","contents":"헤럴드경제<span class=\"txt_bar\"> · </span><span class=\"info_time\">19:04</span>","link":"https://v.daum.net/v/20240306190444426","retrieved":1709720111293},{"title":"Vatican Pope (다음 뉴스 ─ 전체기사 ─ 국제)","contents":"연합뉴스<span class=\"txt_bar\"> · </span><span class=\"info_time\">19:15</span>","link":"https://v.daum.net/v/20240306191500523","retrieved":1709720120084},{"title":"Vatican Pope (다음 뉴스 ─ 전체기사 ─ 국제)","contents":"연합뉴스<span class=\"txt_bar\"> · </span><span class=\"info_time\">19:14</span>","link":"https://v.daum.net/v/20240306191419516","retrieved":1709720120084},{"title":"“주저 없이 트럼프” vs “세계의 웃음거리” (다음 뉴스 ─ 전체기사 ─ 국제)","contents":"채널A<span class=\"txt_bar\"> · </span><span class=\"info_time\">19:09</span>","link":"https://v.daum.net/v/20240306190904462","retrieved":1709720120084},{"title":"푸틴, 그로시 IAEA 사무총장과 자포리자 원전 논의 예정 (다음 뉴스 ─ 전체기사 ─ 국제)","contents":"연합뉴스<span class=\"txt_bar\"> · </span><span class=\"info_time\">19:08</span>","link":"https://v.daum.net/v/20240306190808450","retrieved":1709720120084},{"title":"北 IT기술자에게 부정 송금?…日경찰, 한국 국적자 등 2명 체포 (다음 뉴스 ─ 전체기사 ─ 국제)","contents":"연합뉴스<span class=\"txt_bar\"> · </span><span class=\"info_time\">19:06</span>","link":"https://v.daum.net/v/20240306190616439","retrieved":1709720120084},{"title":"\"3월17일 투표소 향하자\"…나발니 부인, 러 대선날 '反푸틴 시위' 제안 (다음 뉴스 ─ 전체기사 ─ 국제)","contents":"뉴스1<span class=\"txt_bar\"> · </span><span class=\"info_time\">19:05</span>","link":"https://v.daum.net/v/20240306190547432","retrieved":1709720120088},{"title":"WFP \"수단 내전, 최악 기아 위기 촉발할 수도\" (다음 뉴스 ─ 전체기사 ─ 국제)","contents":"연합뉴스<span class=\"txt_bar\"> · </span><span class=\"info_time\">19:04</span>","link":"https://v.daum.net/v/20240306190400410","retrieved":1709720120088},{"title":"바이든 vs 트럼프…4년 만의 재대결 벌인다 (다음 뉴스 ─ 전체기사 ─ 국제)","contents":"채널A<span class=\"txt_bar\"> · </span><span class=\"info_time\">19:02</span>","link":"https://v.daum.net/v/20240306190251390","retrieved":1709720120089},{"title":"유엔 WFP, \"이스라엘군 보름만의 가자북부 구호물자 진입 막아\" (다음 뉴스 ─ 전체기사 ─ 국제)","contents":"뉴시스<span class=\"txt_bar\"> · </span><span class=\"info_time\">19:01</span>","link":"https://v.daum.net/v/20240306190141377","retrieved":1709720120092},{"title":"\"EU도 '영국식 반이민법' 도입을\"… 유럽의회 선거 앞두고 논란 점화 (다음 뉴스 ─ 전체기사 ─ 국제)","contents":"한국일보<span class=\"txt_bar\"> · </span><span class=\"info_time\">19:00</span>","link":"https://v.daum.net/v/20240306190055369","retrieved":1709720120093},{"title":"'잃어버린 30년' 탈출 준비 일본… 증시 활황인데 구조조정 이유는? (다음 뉴스 ─ 전체기사 ─ 국제)","contents":"한국일보<span class=\"txt_bar\"> · </span><span class=\"info_time\">19:00</span>","link":"https://v.daum.net/v/20240306190045362","retrieved":1709720120094},{"title":"日총무성 행정지도 라인야후 \"임원 3명 보수 자진 반납\" (다음 뉴스 ─ 전체기사 ─ 국제)","contents":"아시아경제<span class=\"txt_bar\"> · </span><span class=\"info_time\">19:00</span>","link":"https://v.daum.net/v/20240306190040361","retrieved":1709720120095},{"title":"러-우크라 전선 아프리카로 확대…수단 내전서 '원정 전투' (다음 뉴스 ─ 전체기사 ─ 국제)","contents":"연합뉴스<span class=\"txt_bar\"> · </span><span class=\"info_time\">19:00</span>","link":"https://v.daum.net/v/20240306190010346","retrieved":1709720120097},{"title":"中양회 외교 기자회견, 왕이가 주재…후임 임명 안돼 (다음 뉴스 ─ 전체기사 ─ 국제)","contents":"뉴시스<span class=\"txt_bar\"> · </span><span class=\"info_time\">18:58</span>","link":"https://v.daum.net/v/20240306185802316","retrieved":1709720120098},{"title":"파죽지세 트럼프, 불안한 바이든… ‘리턴 매치’ 사실상 확정 (다음 뉴스 ─ 전체기사 ─ 국제)","contents":"세계일보<span class=\"txt_bar\"> · </span><span class=\"info_time\">18:57</span>","link":"https://v.daum.net/v/20240306185741310","retrieved":1709720120099},{"title":"다목적 소방헬기 도입한 인천소방본부 [포토뉴스] (다음 뉴스 ─ 전체기사 ─ 문화)","contents":"경기일보<span class=\"txt_bar\"> · </span><span class=\"info_time\">19:13</span>","link":"https://v.daum.net/v/20240306191305504","retrieved":1709720126948},{"title":"[날씨] \"전국, 비 내리고 쌀쌀해져요\" (다음 뉴스 ─ 전체기사 ─ 문화)","contents":"아이뉴스24<span class=\"txt_bar\"> · </span><span class=\"info_time\">19:08</span>","link":"https://v.daum.net/v/20240306190817452","retrieved":1709720126950},{"title":"\"아름다운 모습으로 우리를 떠난 그 사람이 그립습니다\" (다음 뉴스 ─ 전체기사 ─ 문화)","contents":"강원도민일보<span class=\"txt_bar\"> · </span><span class=\"info_time\">19:06</span>","link":"https://v.daum.net/v/20240306190626442","retrieved":1709720126952},{"title":"제5회 ‘인카금융 슈퍼볼링’ 8~11일 강릉서 (다음 뉴스 ─ 전체기사 ─ 문화)","contents":"매일경제<span class=\"txt_bar\"> · </span><span class=\"info_time\">19:06</span>","link":"https://v.daum.net/v/20240306190600434","retrieved":1709720126953},{"title":"[단독] “12명 요청했는데 120명이라니” 건대병원 교수들 집단행동 조짐 (다음 뉴스 ─ 전체기사 ─ 문화)","contents":"쿠키뉴스<span class=\"txt_bar\"> · </span><span class=\"info_time\">19:05</span>","link":"https://v.daum.net/v/20240306190502429","retrieved":1709720126955},{"title":"알피바이오, 박재경 신임 대표 내정 (다음 뉴스 ─ 전체기사 ─ 문화)","contents":"서울경제<span class=\"txt_bar\"> · </span><span class=\"info_time\">19:04</span>","link":"https://v.daum.net/v/20240306190419417","retrieved":1709720126956},{"title":"[날씨] 내일 중부·경북 비 또는 눈...\"오후부터 점차 그쳐\" (다음 뉴스 ─ 전체기사 ─ 문화)","contents":"YTN<span class=\"txt_bar\"> · </span><span class=\"info_time\">19:04</span>","link":"https://v.daum.net/v/20240306190414415","retrieved":1709720126958},{"title":"롯데 3세 신유열, 롯바 등기이사 선임···경영승계 위한 신사업 성과 보여줄 시험대 (다음 뉴스 ─ 전체기사 ─ 문화)","contents":"서울경제<span class=\"txt_bar\"> · </span><span class=\"info_time\">19:04</span>","link":"https://v.daum.net/v/20240306190410413","retrieved":1709720126959},{"title":"“앉아 생활하면 하루 9000보 이상 걸어야\" (다음 뉴스 ─ 전체기사 ─ 문화)","contents":"한국경제<span class=\"txt_bar\"> · </span><span class=\"info_time\">19:03</span>","link":"https://v.daum.net/v/20240306190301395","retrieved":1709720126960},{"title":"“교회에 대한 반감요? 오히려 편견 없던데요?” (다음 뉴스 ─ 전체기사 ─ 문화)","contents":"국민일보<span class=\"txt_bar\"> · </span><span class=\"info_time\">19:01</span>","link":"https://v.daum.net/v/20240306190114373","retrieved":1709720126962},{"title":"[포토친구] 토끼가 있는 마을 풍경 (다음 뉴스 ─ 전체기사 ─ 문화)","contents":"포토친구<span class=\"txt_bar\"> · </span><span class=\"info_time\">19:00</span>","link":"https://v.daum.net/v/20240306190024353","retrieved":1709720126964},{"title":"30년 향토서점 계룡문고 흔들… 대전시, 지역서점 외면 (다음 뉴스 ─ 전체기사 ─ 문화)","contents":"대전일보<span class=\"txt_bar\"> · </span><span class=\"info_time\">18:57</span>","link":"https://v.daum.net/v/20240306185701299","retrieved":1709720126965},{"title":"잡채밥 다음은 양참덮밥?! 유지어터 규현의 NEW레시피 (다음 뉴스 ─ 전체기사 ─ 문화)","contents":"코스모폴리탄<span class=\"txt_bar\"> · </span><span class=\"info_time\">18:54</span>","link":"https://v.daum.net/v/20240306185415249","retrieved":1709720126966},{"title":"[오늘의 arte] 도서 증정 이벤트 : 책 '그때 그 사람' (다음 뉴스 ─ 전체기사 ─ 문화)","contents":"한국경제<span class=\"txt_bar\"> · </span><span class=\"info_time\">18:53</span>","link":"https://v.daum.net/v/20240306185302228","retrieved":1709720126968},{"title":"인스파이어, 그랜드 오프닝 행사 성료..\"글로벌 엔터테인먼트 목적지로 본격 도약\" (다음 뉴스 ─ 전체기사 ─ 문화)","contents":"파이낸셜뉴스<span class=\"txt_bar\"> · </span><span class=\"info_time\">18:52</span>","link":"https://v.daum.net/v/20240306185211215","retrieved":1709720126969},{"title":"나훈아는 은퇴했는데…남진 \"가수로 평생? 생각한 적 없다\"('아빠하고') (다음 뉴스 ─ 전체기사 ─ 연예)","contents":"스포츠조선<span class=\"txt_bar\"> · </span><span class=\"info_time\">19:15</span>","link":"https://v.daum.net/v/20240306191519531","retrieved":1709720134108},{"title":"'감스트와 파혼' 뚜밥 \"연애 2년간 스토커에 시달려…사형대 올려진 기분\" (다음 뉴스 ─ 전체기사 ─ 연예)","contents":"헤럴드경제<span class=\"txt_bar\"> · </span><span class=\"info_time\">19:15</span>","link":"https://v.daum.net/v/20240306191514530","retrieved":1709720134109},{"title":"이장우, 타는 목마름으로... \"연기하고 싶지만 내 위치까지 드라마 안 와\" 솔직 (다음 뉴스 ─ 전체기사 ─ 연예)","contents":"TV리포트<span class=\"txt_bar\"> · </span><span class=\"info_time\">19:15</span>","link":"https://v.daum.net/v/20240306191500524","retrieved":1709720134112},{"title":"블랙핑크, '러브식 걸즈' 안무 영상 3억뷰 (다음 뉴스 ─ 전체기사 ─ 연예)","contents":"이데일리<span class=\"txt_bar\"> · </span><span class=\"info_time\">19:13</span>","link":"https://v.daum.net/v/20240306191318508","retrieved":1709720134114},{"title":"케이윌, 감격의 데뷔 17주년 \"변함없이 응원하는 팬 감사\" (다음 뉴스 ─ 전체기사 ─ 연예)","contents":"JTBC<span class=\"txt_bar\"> · </span><span class=\"info_time\">19:12</span>","link":"https://v.daum.net/v/20240306191241498","retrieved":1709720134115},{"title":"‘도시어부5’, 역대급 기상 악화…조기 철수 위기? (다음 뉴스 ─ 전체기사 ─ 연예)","contents":"스포츠동아<span class=\"txt_bar\"> · </span><span class=\"info_time\">19:11</span>","link":"https://v.daum.net/v/20240306191157483","retrieved":1709720134117},{"title":"사진전이 스포였나…류준열X한소희 \"한재림 '현혹' 출연 검토 중\"[종합] (다음 뉴스 ─ 전체기사 ─ 연예)","contents":"스포티비뉴스<span class=\"txt_bar\"> · </span><span class=\"info_time\">19:10</span>","link":"https://v.daum.net/v/20240306191019476","retrieved":1709720134118},{"title":"김신영 ‘전국노래자랑’ 막촬 앞두고 “목소리 안 나와” 급성후두염으로 휴식 [종합] (다음 뉴스 ─ 전체기사 ─ 연예)","contents":"뉴스엔<span class=\"txt_bar\"> · </span><span class=\"info_time\">19:10</span>","link":"https://v.daum.net/v/20240306191011471","retrieved":1709720134121},{"title":"'철옹성' 샤이니도…SM 떠나는 태민, 16년만 '따로 또 같이' [엑's 초점] (다음 뉴스 ─ 전체기사 ─ 연예)","contents":"엑스포츠뉴스<span class=\"txt_bar\"> · </span><span class=\"info_time\">19:10</span>","link":"https://v.daum.net/v/20240306191002469","retrieved":1709720134122},{"title":"이찬원 \"인생 최대 고비? '미스터트롯' 때 14kg 빠져\" (다음 뉴스 ─ 전체기사 ─ 연예)","contents":"JTBC<span class=\"txt_bar\"> · </span><span class=\"info_time\">19:07</span>","link":"https://v.daum.net/v/20240306190740449","retrieved":1709720134124},{"title":"\"연습도 실전처럼\"… 송가인, 전국투어 준비 구슬땀 (다음 뉴스 ─ 전체기사 ─ 연예)","contents":"이데일리<span class=\"txt_bar\"> · </span><span class=\"info_time\">19:05</span>","link":"https://v.daum.net/v/20240306190556433","retrieved":1709720134125},{"title":"'로기완' 송중기 \"수위 센 베드신도 부담 無..감정 공유가 중요\"[인터뷰④] (다음 뉴스 ─ 전체기사 ─ 연예)","contents":"스타뉴스<span class=\"txt_bar\"> · </span><span class=\"info_time\">19:05</span>","link":"https://v.daum.net/v/20240306190500427","retrieved":1709720134129},{"title":"[연예가브리핑] 함은정·장원영…↑김신영↓ (다음 뉴스 ─ 전체기사 ─ 연예)","contents":"머니S<span class=\"txt_bar\"> · </span><span class=\"info_time\">19:04</span>","link":"https://v.daum.net/v/20240306190412414","retrieved":1709720134130},{"title":"이찬원, \"'미스터트롯' 당시 14kg 빠져...다시 돌아가고 싶지 않다\" 고백 (다음 뉴스 ─ 전체기사 ─ 연예)","contents":"스포츠조선<span class=\"txt_bar\"> · </span><span class=\"info_time\">19:03</span>","link":"https://v.daum.net/v/20240306190345407","retrieved":1709720134131},{"title":"'우리가 좋아했던' 가진동, '두통약' 올리며 불쾌함 토로...팬들 걱정 [룩@차이나] (다음 뉴스 ─ 전체기사 ─ 연예)","contents":"TV리포트<span class=\"txt_bar\"> · </span><span class=\"info_time\">19:03</span>","link":"https://v.daum.net/v/20240306190330405","retrieved":1709720134131},{"title":"KLPGA 투어 시즌 대장정 돌입… 박지영, 개막전 '타이틀 방어' 도전 (다음 뉴스 ─ 전체기사 ─ 스포츠)","contents":"머니S<span class=\"txt_bar\"> · </span><span class=\"info_time\">19:13</span>","link":"https://v.daum.net/v/20240306191311505","retrieved":1709720141626},{"title":"임영웅보다 뜨거운 린가드…서울, 홈 개막전 역대 최다 관중 보인다 (다음 뉴스 ─ 전체기사 ─ 스포츠)","contents":"노컷뉴스<span class=\"txt_bar\"> · </span><span class=\"info_time\">19:12</span>","link":"https://v.daum.net/v/20240306191201487","retrieved":1709720141627},{"title":"\"한국시리즈? 한번도 못갔죠\" 동갑내기 친구도, 14년 청춘 바친 팀도 우승했는데…39세 노장의 피가 끓는다 [인터뷰] (다음 뉴스 ─ 전체기사 ─ 스포츠)","contents":"스포츠조선<span class=\"txt_bar\"> · </span><span class=\"info_time\">19:11</span>","link":"https://v.daum.net/v/20240306191145480","retrieved":1709720141627},{"title":"[SPO ISSUE] '절친' 이강인에게 무릎 꿇은 '日 에이스'...첫 UCL에서 최악 부진→'8경기 1도움'으로 마감 (다음 뉴스 ─ 전체기사 ─ 스포츠)","contents":"스포티비뉴스<span class=\"txt_bar\"> · </span><span class=\"info_time\">19:10</span>","link":"https://v.daum.net/v/20240306191005470","retrieved":1709720141628},{"title":"U-20 여자축구, 대만 6-0 완파하며 아시안컵 첫승 (다음 뉴스 ─ 전체기사 ─ 스포츠)","contents":"뉴시스<span class=\"txt_bar\"> · </span><span class=\"info_time\">19:04</span>","link":"https://v.daum.net/v/20240306190432424","retrieved":1709720141628},{"title":"박민지·김민별, 개막전 첫날 '괴물 장타자'와 정면 샷 대결 [KLPGA 하나금융그룹] (다음 뉴스 ─ 전체기사 ─ 스포츠)","contents":"골프한국<span class=\"txt_bar\"> · </span><span class=\"info_time\">19:03</span>","link":"https://v.daum.net/v/20240306190340406","retrieved":1709720141629},{"title":"\"소리 없이 진짜 무서워요\" 초보 아닌 처음. SSG 새 감독은 어떤 리더인가[SC캠프 in 자이] (다음 뉴스 ─ 전체기사 ─ 스포츠)","contents":"스포츠조선<span class=\"txt_bar\"> · </span><span class=\"info_time\">19:02</span>","link":"https://v.daum.net/v/20240306190234388","retrieved":1709720141630},{"title":"더프레이, '보물지도 동굴 참여 인증' 이벤트 진행 (다음 뉴스 ─ 전체기사 ─ 스포츠)","contents":"데일리e스포츠<span class=\"txt_bar\"> · </span><span class=\"info_time\">19:02</span>","link":"https://v.daum.net/v/20240306190216386","retrieved":1709720141633},{"title":"맨시티, 트레블 다큐 넷플 예고편 떴다···흥미진진 스토리 4월2일 공개 (다음 뉴스 ─ 전체기사 ─ 스포츠)","contents":"스포츠경향<span class=\"txt_bar\"> · </span><span class=\"info_time\">19:01</span>","link":"https://v.daum.net/v/20240306190103370","retrieved":1709720141634},{"title":"[오늘의 장면] 종이상자로 눈썰매를 (다음 뉴스 ─ 전체기사 ─ 스포츠)","contents":"MBN<span class=\"txt_bar\"> · </span><span class=\"info_time\">19:00</span>","link":"https://v.daum.net/v/20240306190048365","retrieved":1709720141636},{"title":"‘13안타 4홈런 대폭발’ SSG, 대만 마지막 연습경기 13-1 대승…’최고 145km’ 김광현, 3이닝 5K 1실점 위력투 (다음 뉴스 ─ 전체기사 ─ 스포츠)","contents":"OSEN<span class=\"txt_bar\"> · </span><span class=\"info_time\">19:00</span>","link":"https://v.daum.net/v/20240306190022350","retrieved":1709720141637},{"title":"\"60000명의 팬들이 뒤에 있으면 그들을 느낄 수 있다\"...베르너가 전한 데뷔골의 소감 (다음 뉴스 ─ 전체기사 ─ 스포츠)","contents":"스포탈코리아<span class=\"txt_bar\"> · </span><span class=\"info_time\">19:00</span>","link":"https://v.daum.net/v/20240306190009345","retrieved":1709720141639},{"title":"홀란드가 드디어 '입' 열었다…\"기자님들, 거대한 헤드라인 하나 줄게요! 제 거취에 대한...\" 무슨 말을 했길래? (다음 뉴스 ─ 전체기사 ─ 스포츠)","contents":"마이데일리<span class=\"txt_bar\"> · </span><span class=\"info_time\">19:00</span>","link":"https://v.daum.net/v/20240306190007344","retrieved":1709720141640},{"title":"'전유경·원채은 멀티골' 女축구 U-20 대표팀, 6-0으로 아시안컵 대만전 대승 (다음 뉴스 ─ 전체기사 ─ 스포츠)","contents":"스포츠투데이<span class=\"txt_bar\"> · </span><span class=\"info_time\">19:00</span>","link":"https://v.daum.net/v/20240306190004339","retrieved":1709720141641},{"title":"'주민규-이승우 & 배준호' 클린스만에게 더 화가나는 이유... 황선홍 감독 선택할까? (다음 뉴스 ─ 전체기사 ─ 스포츠)","contents":"OSEN<span class=\"txt_bar\"> · </span><span class=\"info_time\">18:59</span>","link":"https://v.daum.net/v/20240306185924330","retrieved":1709720141643},{"title":"\"통신사업 굉장히 위기\"라던 LGU+ 황현식, 연봉 5.2억 깎았다 (다음 뉴스 ─ 전체기사 ─ IT)","contents":"머니투데이<span class=\"txt_bar\"> · </span><span class=\"info_time\">19:15</span>","link":"https://v.daum.net/v/20240306191505527","retrieved":1709720149619},{"title":"KG이니시스, 자동차금융사업 확장 (다음 뉴스 ─ 전체기사 ─ IT)","contents":"이데일리<span class=\"txt_bar\"> · </span><span class=\"info_time\">19:09</span>","link":"https://v.daum.net/v/20240306190950468","retrieved":1709720149620},{"title":"이스트소프트 AI 아나운서, NIA 사업자 선정평가에 활용 (다음 뉴스 ─ 전체기사 ─ IT)","contents":"이데일리<span class=\"txt_bar\"> · </span><span class=\"info_time\">19:06</span>","link":"https://v.daum.net/v/20240306190634443","retrieved":1709720149621},{"title":"이번엔 총선에 발목?…과학기술계 기관장 선임 지연 수두룩 (다음 뉴스 ─ 전체기사 ─ IT)","contents":"대전일보<span class=\"txt_bar\"> · </span><span class=\"info_time\">19:01</span>","link":"https://v.daum.net/v/20240306190154379","retrieved":1709720149622},{"title":"[기고] AI는 IPTV에겐 선택 아닌 필수 (다음 뉴스 ─ 전체기사 ─ IT)","contents":"이데일리<span class=\"txt_bar\"> · </span><span class=\"info_time\">19:00</span>","link":"https://v.daum.net/v/20240306190040360","retrieved":1709720149623},{"title":"머스크에 소송당한 오픈AI, 반박 성명 내놔 (다음 뉴스 ─ 전체기사 ─ IT)","contents":"지디넷코리아<span class=\"txt_bar\"> · </span><span class=\"info_time\">18:57</span>","link":"https://v.daum.net/v/20240306185718303","retrieved":1709720149624},{"title":"'SM 시세조종' 카카오 배재현 총괄, 보석 석방…구속 4개월만 (다음 뉴스 ─ 전체기사 ─ IT)","contents":"SBS Biz<span class=\"txt_bar\"> · </span><span class=\"info_time\">18:57</span>","link":"https://v.daum.net/v/20240306185701298","retrieved":1709720149626},{"title":"동아에스티 \"항체약물 접합체 시장 진출…암 정복하겠다\" (다음 뉴스 ─ 전체기사 ─ IT)","contents":"한국경제<span class=\"txt_bar\"> · </span><span class=\"info_time\">18:57</span>","link":"https://v.daum.net/v/20240306185701297","retrieved":1709720149627},{"title":"[인사] 디지털플랫폼정부위원회 (다음 뉴스 ─ 전체기사 ─ IT)","contents":"이데일리<span class=\"txt_bar\"> · </span><span class=\"info_time\">18:56</span>","link":"https://v.daum.net/v/20240306185601280","retrieved":1709720149629},{"title":"韓, 초기단계 기술수출에 치중, 후기임상 역량 부족…보완해야 (다음 뉴스 ─ 전체기사 ─ IT)","contents":"한국경제<span class=\"txt_bar\"> · </span><span class=\"info_time\">18:55</span>","link":"https://v.daum.net/v/20240306185504266","retrieved":1709720149630},{"title":"\"한경바이오포럼은 美JP모간헬스케어의 한국판\" (다음 뉴스 ─ 전체기사 ─ IT)","contents":"한국경제<span class=\"txt_bar\"> · </span><span class=\"info_time\">18:53</span>","link":"https://v.daum.net/v/20240306185311230","retrieved":1709720149631},{"title":"[인사]디지털플랫폼정부추진단 (다음 뉴스 ─ 전체기사 ─ IT)","contents":"전자신문<span class=\"txt_bar\"> · </span><span class=\"info_time\">18:53</span>","link":"https://v.daum.net/v/20240306185302229","retrieved":1709720149633},{"title":"트위치 철수 수혜주는 아프리카? 치지직? (다음 뉴스 ─ 전체기사 ─ IT)","contents":"게임톡<span class=\"txt_bar\"> · </span><span class=\"info_time\">18:46</span>","link":"https://v.daum.net/v/20240306184620089","retrieved":1709720149634},{"title":"최주선 삼성디스플레이 사장 “업황 바닥 찍어… 마이크로 OLED 시장 선점 위해 노력” (다음 뉴스 ─ 전체기사 ─ IT)","contents":"조선비즈<span class=\"txt_bar\"> · </span><span class=\"info_time\">18:45</span>","link":"https://v.daum.net/v/20240306184540079","retrieved":1709720149636},{"title":"갤럭시24 울트라, 美 컨슈머 리포트 스마트폰 평가 1위 (다음 뉴스 ─ 전체기사 ─ IT)","contents":"이데일리<span class=\"txt_bar\"> · </span><span class=\"info_time\">18:42</span>","link":"https://v.daum.net/v/20240306184215986","retrieved":1709720149638},{"title":"[사설] 다시 3%대로 뛴 물가 … 뒷북 대증적으로 접근해선 못 잡는다 (다음 뉴스 ─ 전체기사 ─ 칼럼)","contents":"디지털타임스<span class=\"txt_bar\"> · </span><span class=\"info_time\">19:08</span>","link":"https://v.daum.net/v/20240306190822455","retrieved":1709720157558},{"title":"[김인권의 트렌드 인사이트] 日학교 식당의 대변신, 대체 어쨌길래? (다음 뉴스 ─ 전체기사 ─ 칼럼)","contents":"디지털타임스<span class=\"txt_bar\"> · </span><span class=\"info_time\">19:08</span>","link":"https://v.daum.net/v/20240306190819454","retrieved":1709720157559},{"title":"[논설실의 서가] 세계 최고 여성 석학의 새로운 사유 방식 (다음 뉴스 ─ 전체기사 ─ 칼럼)","contents":"디지털타임스<span class=\"txt_bar\"> · </span><span class=\"info_time\">19:08</span>","link":"https://v.daum.net/v/20240306190817451","retrieved":1709720157560},{"title":"[손해복의 백세시대 음식보감] 봄철, 입맛을 되찾아 주는 `냉이` (다음 뉴스 ─ 전체기사 ─ 칼럼)","contents":"디지털타임스<span class=\"txt_bar\"> · </span><span class=\"info_time\">19:04</span>","link":"https://v.daum.net/v/20240306190424420","retrieved":1709720157562},{"title":"[송종훈의 근대뉴스 오디세이] \"재산 쓸 곳에 썼다\", 인창의숙 설립자 손창원의 기부 이유 (다음 뉴스 ─ 전체기사 ─ 칼럼)","contents":"디지털타임스<span class=\"txt_bar\"> · </span><span class=\"info_time\">19:04</span>","link":"https://v.daum.net/v/20240306190421419","retrieved":1709720157563},{"title":"[외신사진 속 이슈人] \"시신 묻을 곳도 없다\", 종말론적 위기 맞은 가자 주민들 (다음 뉴스 ─ 전체기사 ─ 칼럼)","contents":"디지털타임스<span class=\"txt_bar\"> · </span><span class=\"info_time\">19:04</span>","link":"https://v.daum.net/v/20240306190419418","retrieved":1709720157565},{"title":"아인슈타인도 몰랐던 우주를 보여준 13조원짜리 망원경 [천문학자와 함께하는 우주 여행 ] (다음 뉴스 ─ 전체기사 ─ 칼럼)","contents":"한국일보<span class=\"txt_bar\"> · </span><span class=\"info_time\">19:00</span>","link":"https://v.daum.net/v/20240306190020348","retrieved":1709720157566},{"title":"검은 뿔테 안경으로 완성된 한동훈의 '패션 시그니처' [패션 에티켓] (다음 뉴스 ─ 전체기사 ─ 칼럼)","contents":"한국일보<span class=\"txt_bar\"> · </span><span class=\"info_time\">19:00</span>","link":"https://v.daum.net/v/20240306190006342","retrieved":1709720157569},{"title":"[만평] 조기영의 세상터치 2024년 3월 7일 (다음 뉴스 ─ 전체기사 ─ 칼럼)","contents":"서울신문<span class=\"txt_bar\"> · </span><span class=\"info_time\">19:00</span>","link":"https://v.daum.net/v/20240306190002334","retrieved":1709720157570},{"title":"[사설] 제재 남발하는 선거방송심의, 언론에도 ‘입틀막’인가 (다음 뉴스 ─ 전체기사 ─ 칼럼)","contents":"한겨레<span class=\"txt_bar\"> · </span><span class=\"info_time\">18:55</span>","link":"https://v.daum.net/v/20240306185508267","retrieved":1709720157572},{"title":"[사설] 尹 \"비상진료체계 가동\"… 신속 과감히 실행해 국민 불안 덜어야 (다음 뉴스 ─ 전체기사 ─ 칼럼)","contents":"디지털타임스<span class=\"txt_bar\"> · </span><span class=\"info_time\">18:45</span>","link":"https://v.daum.net/v/20240306184523071","retrieved":1709720157575},{"title":"[fn사설] 낙제 못 면한 노동시장, 개혁의 칼 다시 들어야 (다음 뉴스 ─ 전체기사 ─ 칼럼)","contents":"파이낸셜뉴스<span class=\"txt_bar\"> · </span><span class=\"info_time\">18:40</span>","link":"https://v.daum.net/v/20240306184018932","retrieved":1709720157576},{"title":"[fn사설] 독점적 의사 카르텔 깰 방안 서서히 고민을 (다음 뉴스 ─ 전체기사 ─ 칼럼)","contents":"파이낸셜뉴스<span class=\"txt_bar\"> · </span><span class=\"info_time\">18:40</span>","link":"https://v.daum.net/v/20240306184008925","retrieved":1709720157578},{"title":"[fn광장] 혼돈의 시대에 나타난 '인공 神' AI (다음 뉴스 ─ 전체기사 ─ 칼럼)","contents":"파이낸셜뉴스<span class=\"txt_bar\"> · </span><span class=\"info_time\">18:40</span>","link":"https://v.daum.net/v/20240306184002918","retrieved":1709720157579},{"title":"[노동일의 세상만사] '대통령 배우자 공격'으로 총선 치르려는 野 (다음 뉴스 ─ 전체기사 ─ 칼럼)","contents":"파이낸셜뉴스<span class=\"txt_bar\"> · </span><span class=\"info_time\">18:37</span>","link":"https://v.daum.net/v/20240306183714877","retrieved":1709720157581},{"title":"[PRNewswire] COMPUTEX 2024, AI 거장 대거 출격 (다음 뉴스 ─ 전체기사 ─ 보도자료)","contents":"연합뉴스 보도자료<span class=\"txt_bar\"> · </span><span class=\"info_time\">19:12</span>","link":"https://v.daum.net/v/20240306191240497","retrieved":1709720164795},{"title":"[PRNewswire] iQIYI Expands Offline VR Immersive Theater into Xi'an (다음 뉴스 ─ 전체기사 ─ 보도자료)","contents":"연합뉴스 보도자료<span class=\"txt_bar\"> · </span><span class=\"info_time\">19:09</span>","link":"https://v.daum.net/v/20240306190947467","retrieved":1709720164796},{"title":"[4·10 총선 공약매치] '분구'vs'제2구청사'… 대전 서구갑 정책대결 활활 (다음 뉴스 ─ 전체기사 ─ 보도자료)","contents":"대전일보<span class=\"txt_bar\"> · </span><span class=\"info_time\">18:52</span>","link":"https://v.daum.net/v/20240306185203212","retrieved":1709720164797},{"title":"[자막뉴스] 4년 만에 열린 전국 재난 대비 훈련 (다음 뉴스 ─ 전체기사 ─ 보도자료)","contents":"강원도민일보<span class=\"txt_bar\"> · </span><span class=\"info_time\">18:20</span>","link":"https://v.daum.net/v/20240306182027516","retrieved":1709720164799},{"title":"최대호 안양시장, 세 쌍둥이 가정 2곳 기업 지원 연계 및 축하 방문 (다음 뉴스 ─ 전체기사 ─ 보도자료)","contents":"데일리안<span class=\"txt_bar\"> · </span><span class=\"info_time\">18:20</span>","link":"https://v.daum.net/v/20240306182000504","retrieved":1709720164801},{"title":"[PRNewswire] CGTN: 시 주석, 현지 상황에 맞는 양질의 새로운 생산력 개발 강조 (다음 뉴스 ─ 전체기사 ─ 보도자료)","contents":"연합뉴스 보도자료<span class=\"txt_bar\"> · </span><span class=\"info_time\">18:16</span>","link":"https://v.daum.net/v/20240306181647443","retrieved":1709720164806},{"title":"[PRNewswire] CGTN: Xi stresses developing new quality productive forces (다음 뉴스 ─ 전체기사 ─ 보도자료)","contents":"연합뉴스 보도자료<span class=\"txt_bar\"> · </span><span class=\"info_time\">18:14</span>","link":"https://v.daum.net/v/20240306181450381","retrieved":1709716548104},{"title":"\"메타버스로 수서역 방문하고 SRT 운임할인권 받으세요\" (다음 뉴스 ─ 전체기사 ─ 보도자료)","contents":"투어코리아<span class=\"txt_bar\"> · </span><span class=\"info_time\">18:08</span>","link":"https://v.daum.net/v/20240306180840216","retrieved":1709716548106},{"title":"최영일 순창군수 “포트홀 보수 유지보수 가용 예산 적극 투입” (다음 뉴스 ─ 전체기사 ─ 보도자료)","contents":"스포츠동아<span class=\"txt_bar\"> · </span><span class=\"info_time\">18:01</span>","link":"https://v.daum.net/v/20240306180141991","retrieved":1709716548108},{"title":"목포시, 조선산업 고충 해소 다각도 지원 (다음 뉴스 ─ 전체기사 ─ 보도자료)","contents":"스포츠동아<span class=\"txt_bar\"> · </span><span class=\"info_time\">18:01</span>","link":"https://v.daum.net/v/20240306180101968","retrieved":1709716548109},{"title":"[PRNewswire] COMPUTEX 2024 Unveils AI Powerhouses (다음 뉴스 ─ 전체기사 ─ 보도자료)","contents":"연합뉴스 보도자료<span class=\"txt_bar\"> · </span><span class=\"info_time\">17:58</span>","link":"https://v.daum.net/v/20240306175820836","retrieved":1709716548111},{"title":"[PRNewswire] 하겐다즈, 글로벌 캠페인 '로즈 프로젝트' 수상자 5명 발표 (다음 뉴스 ─ 전체기사 ─ 보도자료)","contents":"연합뉴스 보도자료<span class=\"txt_bar\"> · </span><span class=\"info_time\">17:44</span>","link":"https://v.daum.net/v/20240306174452301","retrieved":1709716548112},{"title":"[PRNewswire] LAMPRO International Distributor Summit: 함께 모여 미래 전망 (다음 뉴스 ─ 전체기사 ─ 보도자료)","contents":"연합뉴스 보도자료<span class=\"txt_bar\"> · </span><span class=\"info_time\">17:44</span>","link":"https://v.daum.net/v/20240306174451300","retrieved":1709716548114},{"title":"세종사이버대학교 유통물류학과 백소라 교수, ‘한국드론배송협회’ 초대회장 선출 (다음 뉴스 ─ 전체기사 ─ 보도자료)","contents":"중앙일보<span class=\"txt_bar\"> · </span><span class=\"info_time\">17:30</span>","link":"https://v.daum.net/v/20240306173052844","retrieved":1709716548115},{"title":"살조물질에 대한 독성 플랑크톤의 글루타치온-S-전이효소 유전자 반응 및 세포예정자살 현상 최초 규명 (다음 뉴스 ─ 전체기사 ─ 보도자료)","contents":"중앙일보<span class=\"txt_bar\"> · </span><span class=\"info_time\">17:30</span>","link":"https://v.daum.net/v/20240306173010794","retrieved":1709716548117},{"title":"06일, 기관 코스닥에서 레고켐바이오(+29.33%), 에코프로비엠(-2.35%) 등 순매도 (다음 뉴스 ─ 전체기사 ─ 자동생성기사)","contents":"한국경제<span class=\"txt_bar\"> · </span><span class=\"info_time\">18:36</span>","link":"https://v.daum.net/v/20240306183616857","retrieved":1709720171960},{"title":"06일, 코스닥 외국인 순매도상위에 제약 업종 5종목 (다음 뉴스 ─ 전체기사 ─ 자동생성기사)","contents":"한국경제<span class=\"txt_bar\"> · </span><span class=\"info_time\">18:36</span>","link":"https://v.daum.net/v/20240306183614856","retrieved":1709720171962},{"title":"06일, 코스닥 기관 순매수상위에 반도체 업종 8종목 (다음 뉴스 ─ 전체기사 ─ 자동생성기사)","contents":"한국경제<span class=\"txt_bar\"> · </span><span class=\"info_time\">18:36</span>","link":"https://v.daum.net/v/20240306183613854","retrieved":1709720171964},{"title":"06일, 외국인 코스닥에서 동진쎄미켐(+9.35%), 레인보우로보틱스(+3.12%) 등 순매수 (다음 뉴스 ─ 전체기사 ─ 자동생성기사)","contents":"한국경제<span class=\"txt_bar\"> · </span><span class=\"info_time\">18:36</span>","link":"https://v.daum.net/v/20240306183611853","retrieved":1709720171965},{"title":"06일, 거래소 기관 순매도상위에 전기,전자 업종 5종목 (다음 뉴스 ─ 전체기사 ─ 자동생성기사)","contents":"한국경제<span class=\"txt_bar\"> · </span><span class=\"info_time\">18:36</span>","link":"https://v.daum.net/v/20240306183609852","retrieved":1709720171966},{"title":"06일, 거래소 외국인 순매도상위에 전기,전자 업종 7종목 (다음 뉴스 ─ 전체기사 ─ 자동생성기사)","contents":"한국경제<span class=\"txt_bar\"> · </span><span class=\"info_time\">18:36</span>","link":"https://v.daum.net/v/20240306183608849","retrieved":1709720171968},{"title":"06일, 기관 거래소에서 한국전력(+0.82%), 삼성엔지니어링(+3.13%) 등 순매수 (다음 뉴스 ─ 전체기사 ─ 자동생성기사)","contents":"한국경제<span class=\"txt_bar\"> · </span><span class=\"info_time\">18:36</span>","link":"https://v.daum.net/v/20240306183606848","retrieved":1709720171971},{"title":"06일, 외국인 거래소에서 LIG넥스원(+10.64%), 신한지주(+3.52%) 등 순매수 (다음 뉴스 ─ 전체기사 ─ 자동생성기사)","contents":"한국경제<span class=\"txt_bar\"> · </span><span class=\"info_time\">18:36</span>","link":"https://v.daum.net/v/20240306183605846","retrieved":1709720171972},{"title":"풍산 수주공시 - 소구경탄약 공급계약 2,282.5억원 (매출액대비  5.2 %) (다음 뉴스 ─ 전체기사 ─ 자동생성기사)","contents":"한국경제<span class=\"txt_bar\"> · </span><span class=\"info_time\">18:11</span>","link":"https://v.daum.net/v/20240306181108288","retrieved":1709716557446},{"title":"한신공영 수주공시 - 345kV 고덕-서안성TL 건설공사 325.3억원 (매출액대비  2.7 %) (다음 뉴스 ─ 전체기사 ─ 자동생성기사)","contents":"한국경제<span class=\"txt_bar\"> · </span><span class=\"info_time\">17:46</span>","link":"https://v.daum.net/v/20240306174607370","retrieved":1709716557448},{"title":"오늘의 날씨 - 오후 (2024년 03월 06일) (다음 뉴스 ─ 전체기사 ─ 자동생성기사)","contents":"국민일보<span class=\"txt_bar\"> · </span><span class=\"info_time\">17:33</span>","link":"https://v.daum.net/v/20240306173315933","retrieved":1709716557449},{"title":"국고채 금리 일제히 하락…3년물 연 3.325% (다음 뉴스 ─ 전체기사 ─ 자동생성기사)","contents":"연합뉴스<span class=\"txt_bar\"> · </span><span class=\"info_time\">16:42</span>","link":"https://v.daum.net/v/20240306164214896","retrieved":1709713217991},{"title":"서한 수주공시 - 서울 둔촌동역 역세권 주상복합 신축공사 615.8억원 (매출액대비  8.37 %) (다음 뉴스 ─ 전체기사 ─ 자동생성기사)","contents":"한국경제<span class=\"txt_bar\"> · </span><span class=\"info_time\">16:36</span>","link":"https://v.daum.net/v/20240306163604655","retrieved":1709713217991},{"title":"'플레이디' 52주 신고가 경신, 전일 외국인 대량 순매수 (다음 뉴스 ─ 전체기사 ─ 자동생성기사)","contents":"한국경제<span class=\"txt_bar\"> · </span><span class=\"info_time\">15:35</span>","link":"https://v.daum.net/v/20240306153507858","retrieved":1709709281892},{"title":"KC코트렐, 176억원 3자배정 유상증자 (다음 뉴스 ─ 전체기사 ─ 자동생성기사)","contents":"연합뉴스<span class=\"txt_bar\"> · </span><span class=\"info_time\">15:27</span>","link":"https://v.daum.net/v/20240306152731427","retrieved":1709709281895}]}