{"title":"다음 뉴스 ─ 전체기사 ─ 연예","url":"https://news.daum.net/breakingnews/entertain","favicon":"https://news.daum.net/breakingnews/favicon.ico","elements":[{"title":"가왕의 귀환… 조용필, 11월 20집 발매 기념 콘서트","contents":"국민일보<span class=\"txt_bar\"> · </span><span class=\"info_time\">02:14</span>","link":"https://v.daum.net/v/20241009021416464","retrieved":1728407825893},{"title":"[And 방송·문화] 미워할 수 없는 빌런, 서동재가 돌아왔다","contents":"국민일보<span class=\"txt_bar\"> · </span><span class=\"info_time\">02:13</span>","link":"https://v.daum.net/v/20241009021316462","retrieved":1728407825895},{"title":"‘PROJECT 7(프로젝트 7)’, 최애 참가자 선택을 위한 순간이 다가온다!","contents":"스포츠경향<span class=\"txt_bar\"> · </span><span class=\"info_time\">02:05</span>","link":"https://v.daum.net/v/20241009020512455","retrieved":1728407825896},{"title":"레드벨벳 슬기, 10년 만에 단발 변신…잘 어울리네","contents":"마이데일리<span class=\"txt_bar\"> · </span><span class=\"info_time\">02:00</span>","link":"https://v.daum.net/v/20241009020005445","retrieved":1728407825898},{"title":"‘열애 중’ 심현섭, 실전상황 투입? 전투 발발에 “실제 뉴스 같아” (리얼전투 48)","contents":"스포츠경향<span class=\"txt_bar\"> · </span><span class=\"info_time\">01:59</span>","link":"https://v.daum.net/v/20241009015924443","retrieved":1728407825900},{"title":"HYNN(박혜원), 신곡 ‘오늘 노을이 예뻐서’ 뮤직비디오 티저 공개","contents":"스포츠경향<span class=\"txt_bar\"> · </span><span class=\"info_time\">01:54</span>","link":"https://v.daum.net/v/20241009015448435","retrieved":1728407825902},{"title":"더핑크퐁컴퍼니, 부천국제애니메이션페스티벌(BIAF) 애니메이션 최다 초청","contents":"스포츠경향<span class=\"txt_bar\"> · </span><span class=\"info_time\">01:46</span>","link":"https://v.daum.net/v/20241009014633412","retrieved":1728407825905},{"title":"'트롯 걸즈 재팬' 준우승 우타고코로 리에, 21일 韓 첫 싱글 '제비꽃' 발매 [공식]","contents":"OSEN<span class=\"txt_bar\"> · </span><span class=\"info_time\">01:44</span>","link":"https://v.daum.net/v/20241009014420409","retrieved":1728407825905},{"title":"[오늘의 채널A]심형탁, 日로 떠난 태교여행서 처가식구 상봉","contents":"동아일보<span class=\"txt_bar\"> · </span><span class=\"info_time\">01:42</span>","link":"https://v.daum.net/v/20241009014217384","retrieved":1728407825907},{"title":"'♥공개연애 도전' 오윤아 \"알러뷰\"…아들 향한 애정 표현","contents":"뉴시스<span class=\"txt_bar\"> · </span><span class=\"info_time\">01:35</span>","link":"https://v.daum.net/v/20241009013508333","retrieved":1728407825908},{"title":"'임성빈♥' 신다은 \"홀로 급 여행→아기모델 子 안 찾아 당황스럽지만 신나\"","contents":"마이데일리<span class=\"txt_bar\"> · </span><span class=\"info_time\">01:30</span>","link":"https://v.daum.net/v/20241009013007309","retrieved":1728407825910},{"title":"신유, 전유진 노래 실력 극찬…“진짜 완벽” (‘한일톱텐쇼’)","contents":"스타투데이<span class=\"txt_bar\"> · </span><span class=\"info_time\">01:15</span>","link":"https://v.daum.net/v/20241009011500246","retrieved":1728404636592},{"title":"'플로리다 프로젝트' 감독, 젊은 거장 션 베이커 신작 '아노라' 개봉","contents":"MHN스포츠<span class=\"txt_bar\"> · </span><span class=\"info_time\">01:00</span>","link":"https://v.daum.net/v/20241009010005159","retrieved":1728404636595},{"title":"설운도 “신유 아직 살아있어” 칭찬…신유 “내가 언제 죽었었냐” (‘한일톱텐쇼’)","contents":"스타투데이<span class=\"txt_bar\"> · </span><span class=\"info_time\">00:57</span>","link":"https://v.daum.net/v/20241009005700152","retrieved":1728404636595},{"title":"우지원 \"전처와 2년 별거 후 이혼.. 경찰 출동한 사건 때문 아냐\"(이제혼자다)","contents":"MBC연예<span class=\"txt_bar\"> · </span><span class=\"info_time\">00:55</span>","link":"https://v.daum.net/v/20241009005531141","retrieved":1728404636596}]}