{"title":"다음 뉴스 ─ 전체기사 ─ 국제","url":"https://news.daum.net/breakingnews/foreign","favicon":"https://news.daum.net/breakingnews/favicon.ico","elements":[{"title":"Azerbaijan Turkey","contents":"연합뉴스<span class=\"txt_bar\"> · </span><span class=\"info_time\">01:27</span>","link":"https://v.daum.net/v/20220529012700002","retrieved":1653755239194},{"title":"Azerbaijan Turkey","contents":"연합뉴스<span class=\"txt_bar\"> · </span><span class=\"info_time\">01:26</span>","link":"https://v.daum.net/v/20220529012656001","retrieved":1653755239194},{"title":"France Tennis French Open","contents":"연합뉴스<span class=\"txt_bar\"> · </span><span class=\"info_time\">01:26</span>","link":"https://v.daum.net/v/20220529012653000","retrieved":1653755239201},{"title":"Azerbaijan Turkey","contents":"연합뉴스<span class=\"txt_bar\"> · </span><span class=\"info_time\">01:26</span>","link":"https://v.daum.net/v/20220529012634996","retrieved":1653755239204},{"title":"epaselect SPAIN ARMED FORCES DAY","contents":"연합뉴스<span class=\"txt_bar\"> · </span><span class=\"info_time\">01:25</span>","link":"https://v.daum.net/v/20220529012548994","retrieved":1653755239205},{"title":"epaselect PAKISTAN WEATHER HEATWAVE","contents":"연합뉴스<span class=\"txt_bar\"> · </span><span class=\"info_time\">01:25</span>","link":"https://v.daum.net/v/20220529012542992","retrieved":1653755239206},{"title":"Russia Ukraine War","contents":"연합뉴스<span class=\"txt_bar\"> · </span><span class=\"info_time\">01:25</span>","link":"https://v.daum.net/v/20220529012538991","retrieved":1653755239208},{"title":"epaselect UKRAINE RUSSIA CONFLICT","contents":"연합뉴스<span class=\"txt_bar\"> · </span><span class=\"info_time\">01:25</span>","link":"https://v.daum.net/v/20220529012535990","retrieved":1653755239209},{"title":"epaselect UKRAINE RUSSIA CONFLICT","contents":"연합뉴스<span class=\"txt_bar\"> · </span><span class=\"info_time\">01:25</span>","link":"https://v.daum.net/v/20220529012531989","retrieved":1653755239210},{"title":"France Tennis French Open","contents":"연합뉴스<span class=\"txt_bar\"> · </span><span class=\"info_time\">01:25</span>","link":"https://v.daum.net/v/20220529012528988","retrieved":1653755239211},{"title":"Biden Delaware","contents":"연합뉴스<span class=\"txt_bar\"> · </span><span class=\"info_time\">01:25</span>","link":"https://v.daum.net/v/20220529012510987","retrieved":1653755239211},{"title":"Italy Giro Cycling","contents":"연합뉴스<span class=\"txt_bar\"> · </span><span class=\"info_time\">01:25</span>","link":"https://v.daum.net/v/20220529012507986","retrieved":1653755239213},{"title":"Biden Delaware","contents":"연합뉴스<span class=\"txt_bar\"> · </span><span class=\"info_time\">01:25</span>","link":"https://v.daum.net/v/20220529012503985","retrieved":1653755239215},{"title":"Election 2022 Georgia Senate Black Candidates","contents":"연합뉴스<span class=\"txt_bar\"> · </span><span class=\"info_time\">01:25</span>","link":"https://v.daum.net/v/20220529012500984","retrieved":1653755239216},{"title":"Texas School Shooting","contents":"연합뉴스<span class=\"txt_bar\"> · </span><span class=\"info_time\">01:24</span>","link":"https://v.daum.net/v/20220529012456983","retrieved":1653755239218}]}