{"title":"다음 뉴스 ─ 전체기사 ─ 정치","url":"https://news.daum.net/breakingnews/politics","favicon":"https://news.daum.net/breakingnews/favicon.ico","elements":[{"title":"'윷을 던져보자'","contents":"연합뉴스<span class=\"txt_bar\"> · </span><span class=\"info_time\">12:18</span>","link":"https://v.daum.net/v/20230119121855163","retrieved":1674098352435},{"title":"'윷을 던져보자'","contents":"연합뉴스<span class=\"txt_bar\"> · </span><span class=\"info_time\">12:18</span>","link":"https://v.daum.net/v/20230119121851161","retrieved":1674098352440},{"title":"'윷을 던져보자'","contents":"연합뉴스<span class=\"txt_bar\"> · </span><span class=\"info_time\">12:18</span>","link":"https://v.daum.net/v/20230119121848158","retrieved":1674098352440},{"title":"'투호 던지기 너무 즐거워요'","contents":"연합뉴스<span class=\"txt_bar\"> · </span><span class=\"info_time\">12:18</span>","link":"https://v.daum.net/v/20230119121844157","retrieved":1674098352440},{"title":"'투호 던지기는 즐겁게'","contents":"연합뉴스<span class=\"txt_bar\"> · </span><span class=\"info_time\">12:18</span>","link":"https://v.daum.net/v/20230119121841156","retrieved":1674098352441},{"title":"'투호 던지기 너무 즐거워요'","contents":"연합뉴스<span class=\"txt_bar\"> · </span><span class=\"info_time\">12:18</span>","link":"https://v.daum.net/v/20230119121837155","retrieved":1674098352441},{"title":"'투호 던지기는 즐겁게'","contents":"연합뉴스<span class=\"txt_bar\"> · </span><span class=\"info_time\">12:18</span>","link":"https://v.daum.net/v/20230119121834154","retrieved":1674098352441},{"title":"'윷놀이 처음이지만 재미있어요'","contents":"연합뉴스<span class=\"txt_bar\"> · </span><span class=\"info_time\">12:18</span>","link":"https://v.daum.net/v/20230119121826153","retrieved":1674098352443},{"title":"[포토] '고향사랑기부제' 캠페인","contents":"이데일리<span class=\"txt_bar\"> · </span><span class=\"info_time\">12:18</span>","link":"https://v.daum.net/v/20230119121824152","retrieved":1674098352444},{"title":"北 최고인민회의, 김정은 '쏙' 빠진 배경은?(종합)","contents":"아시아경제<span class=\"txt_bar\"> · </span><span class=\"info_time\">12:18</span>","link":"https://v.daum.net/v/20230119121817151","retrieved":1674098352445},{"title":"태영호, 최고위 출마선언 “김정은이 가장 두려워할 것”","contents":"시사저널<span class=\"txt_bar\"> · </span><span class=\"info_time\">12:18</span>","link":"https://v.daum.net/v/20230119121802140","retrieved":1674098352446},{"title":"6개월 만에 호남 찾은 국민의힘 지도부 “5·18 정신 이어갈 것”","contents":"경향신문<span class=\"txt_bar\"> · </span><span class=\"info_time\">12:17</span>","link":"https://v.daum.net/v/20230119121747132","retrieved":1674098352447},{"title":"[포토] '고향사랑기부제' 홍보 캠페인","contents":"이데일리<span class=\"txt_bar\"> · </span><span class=\"info_time\">12:16</span>","link":"https://v.daum.net/v/20230119121652123","retrieved":1674098352448},{"title":"'북 공작원 접촉의혹' 민노총 간부 주거지 압수수색","contents":"SBS<span class=\"txt_bar\"> · </span><span class=\"info_time\">12:15</span>","link":"https://v.daum.net/v/20230119121508098","retrieved":1674098352450},{"title":"[포토] 농협, '고향사랑기부제' 홍보 캠페인","contents":"이데일리<span class=\"txt_bar\"> · </span><span class=\"info_time\">12:15</span>","link":"https://v.daum.net/v/20230119121506095","retrieved":1674098352451}]}