{"title":"다음 뉴스 ─ 전체기사 ─ 사회","url":"https://news.daum.net/breakingnews/society","favicon":"https://news.daum.net/breakingnews/favicon.ico","elements":[{"title":"[제보는Y] '시동 꺼짐' 결함 잇따르는데..\"점검 결과 이상 없다\"는 벤츠","contents":"YTN<span class=\"txt_bar\"> · </span><span class=\"info_time\">05:22</span>","link":"https://v.daum.net/v/20220913052214854","retrieved":1663014191812},{"title":"\"자격 논란 있는데\"..인천 앞바다 해상풍력 또 '시끌'","contents":"노컷뉴스<span class=\"txt_bar\"> · </span><span class=\"info_time\">05:21</span>","link":"https://v.daum.net/v/20220913052100847","retrieved":1663014191812},{"title":"오후 9시까지 전국 5만4731명 확진..연휴 이후 유행 추이는","contents":"한국경제TV<span class=\"txt_bar\"> · </span><span class=\"info_time\">05:19</span>","link":"https://v.daum.net/v/20220913051947833","retrieved":1663014191814},{"title":"'공포의 10분'..용인 놀이공원서 롤러코스터 20m 높이서 멈춰","contents":"한국경제TV<span class=\"txt_bar\"> · </span><span class=\"info_time\">05:18</span>","link":"https://v.daum.net/v/20220913051833830","retrieved":1663014191814},{"title":"반포 한강공원에서 갑자기 불어난 물에 시민 대피","contents":"YTN<span class=\"txt_bar\"> · </span><span class=\"info_time\">05:15</span>","link":"https://v.daum.net/v/20220913051502775","retrieved":1663014191820},{"title":"천안서 승용차 논으로 추락..20대 운전자 심정지","contents":"YTN<span class=\"txt_bar\"> · </span><span class=\"info_time\">05:15</span>","link":"https://v.daum.net/v/20220913051500774","retrieved":1663014191821},{"title":"돌고 돌아 '기재부 출신' 복지장관..조규홍 후보자 과제는?","contents":"노컷뉴스<span class=\"txt_bar\"> · </span><span class=\"info_time\">05:12</span>","link":"https://v.daum.net/v/20220913051201740","retrieved":1663014191821},{"title":"'동해→일본해'.. 해외 유명사전들 살펴보니","contents":"머니S<span class=\"txt_bar\"> · </span><span class=\"info_time\">05:11</span>","link":"https://v.daum.net/v/20220913051107736","retrieved":1663014191822},{"title":"울산 이예로, 9월 말 완전 개통..착공 12년만","contents":"뉴스1<span class=\"txt_bar\"> · </span><span class=\"info_time\">05:10</span>","link":"https://v.daum.net/v/20220913051006723","retrieved":1663014191823},{"title":"울산시, 민선 8기 '시정 비전' 새 디자인 확정","contents":"뉴스1<span class=\"txt_bar\"> · </span><span class=\"info_time\">05:10</span>","link":"https://v.daum.net/v/20220913051003720","retrieved":1663014191824},{"title":"[날씨] 전국 대체로 흐리고 비 곳곳..제주·남해 풍랑특보","contents":"MBC<span class=\"txt_bar\"> · </span><span class=\"info_time\">05:09</span>","link":"https://v.daum.net/v/20220913050901710","retrieved":1663014191825},{"title":"500만원 못갚아서..청년들 \\'빚의 족쇄\\'","contents":"한겨레<span class=\"txt_bar\"> · </span><span class=\"info_time\">05:05</span>","link":"https://v.daum.net/v/20220913050536683","retrieved":1663014191827},{"title":"반지하에서 힘들고, 괴롭지만..\"아들도 '우영우'처럼 홀로 설수 있을까\"","contents":"한겨레<span class=\"txt_bar\"> · </span><span class=\"info_time\">05:05</span>","link":"https://v.daum.net/v/20220913050532682","retrieved":1663014191828},{"title":"\"선수 믿고 기다려준 그 마음이 '한국 역도 메달밭' 일궈냈지요\"","contents":"한겨레<span class=\"txt_bar\"> · </span><span class=\"info_time\">05:05</span>","link":"https://v.daum.net/v/20220913050526681","retrieved":1663014191831},{"title":"[영상:THISCovery]옛날엔 배가 지나갈 때 잠수교가 좌·우로 열렸다?","contents":"한겨레<span class=\"txt_bar\"> · </span><span class=\"info_time\">05:05</span>","link":"https://v.daum.net/v/20220913050520680","retrieved":1663014191834}]}